{"displayFieldName":"TOWNNAME","fieldAliases":{"ID":"ID","DIS_CODE":"DIS_CODE","TOWNNAME":"TOWNNAME","LI":"LI","LIN":"LIN","STREET":"STREET","SECT":"SECT","MAREA":"MAREA","LANE":"LANE","ALLEY":"ALLEY","HOUSE_NO":"HOUSE_NO","E_COORD97":"E_COORD97","N_COORD97":"N_COORD97","ADDRESS":"ADDRESS","OBJECTID":"OBJECTID"},"geometryType":"esriGeometryPoint","spatialReference":{"wkid":102443,"latestWkid":3826},"fields":[{"name":"ID","type":"esriFieldTypeDouble","alias":"ID"},{"name":"DIS_CODE","type":"esriFieldTypeInteger","alias":"DIS_CODE"},{"name":"TOWNNAME","type":"esriFieldTypeString","alias":"TOWNNAME","length":8},{"name":"LI","type":"esriFieldTypeString","alias":"LI","length":8},{"name":"LIN","type":"esriFieldTypeString","alias":"LIN","length":12},{"name":"STREET","type":"esriFieldTypeString","alias":"STREET","length":20},{"name":"SECT","type":"esriFieldTypeString","alias":"SECT","length":8},{"name":"MAREA","type":"esriFieldTypeString","alias":"MAREA","length":12},{"name":"LANE","type":"esriFieldTypeString","alias":"LANE","length":10},{"name":"ALLEY","type":"esriFieldTypeString","alias":"ALLEY","length":10},{"name":"HOUSE_NO","type":"esriFieldTypeString","alias":"HOUSE_NO","length":20},{"name":"E_COORD97","type":"esriFieldTypeDouble","alias":"E_COORD97"},{"name":"N_COORD97","type":"esriFieldTypeDouble","alias":"N_COORD97"},{"name":"ADDRESS","type":"esriFieldTypeString","alias":"ADDRESS","length":50},{"name":"OBJECTID","type":"esriFieldTypeOID","alias":"OBJECTID"}],"features":[{"attributes":{"ID":266405,"DIS_CODE":0,"TOWNNAME":"安南區","LI":"溪心里","LIN":"14鄰","STREET":"本原街","SECT":"二段","MAREA":" ","LANE":"５３２巷","ALLEY":" ","HOUSE_NO":"３號","E_COORD97":165821.17999999999,"N_COORD97":2550512.96,"ADDRESS":"本原街二段５３２巷３號","OBJECTID":266401},"geometry":{"x":165821.1799999997,"y":2550512.9600000009}},{"attributes":{"ID":266406,"DIS_CODE":0,"TOWNNAME":"安南區","LI":"溪心里","LIN":"14鄰","STREET":"本原街","SECT":"二段","MAREA":" ","LANE":"５３２巷","ALLEY":" ","HOUSE_NO":"４號","E_COORD97":165843.92000000001,"N_COORD97":2550527.5499999998,"ADDRESS":"本原街二段５３２巷４號","OBJECTID":266402},"geometry":{"x":165843.92000000179,"y":2550527.5500000045}},{"attributes":{"ID":266407,"DIS_CODE":0,"TOWNNAME":"安南區","LI":"溪心里","LIN":"14鄰","STREET":"本原街","SECT":"二段","MAREA":" ","LANE":"５３２巷","ALLEY":" ","HOUSE_NO":"６號","E_COORD97":165840.88,"N_COORD97":2550530.8300000001,"ADDRESS":"本原街二段５３２巷６號","OBJECTID":266403},"geometry":{"x":165840.88000000082,"y":2550530.8300000001}},{"attributes":{"ID":266408,"DIS_CODE":0,"TOWNNAME":"安南區","LI":"溪心里","LIN":"14鄰","STREET":"本原街","SECT":"二段","MAREA":" ","LANE":"５３２巷","ALLEY":" ","HOUSE_NO":"７號","E_COORD97":165815.22,"N_COORD97":2550523.7799999998,"ADDRESS":"本原街二段５３２巷７號","OBJECTID":266404},"geometry":{"x":165815.22000000067,"y":2550523.7799999993}},{"attributes":{"ID":266409,"DIS_CODE":0,"TOWNNAME":"安南區","LI":"溪心里","LIN":"14鄰","STREET":"本原街","SECT":"二段","MAREA":" ","LANE":"５３２巷","ALLEY":" ","HOUSE_NO":"８號","E_COORD97":165838.32000000001,"N_COORD97":2550534.3500000001,"ADDRESS":"本原街二段５３２巷８號","OBJECTID":266405},"geometry":{"x":165838.32000000123,"y":2550534.3500000034}},{"attributes":{"ID":266410,"DIS_CODE":0,"TOWNNAME":"安南區","LI":"城東里","LIN":"14鄰","STREET":"城北路","SECT":" ","MAREA":" ","LANE":"２６８巷","ALLEY":" ","HOUSE_NO":"１７號","E_COORD97":160987.64000000001,"N_COORD97":2551962.6099999999,"ADDRESS":"城北路２６８巷１７號","OBJECTID":266406},"geometry":{"x":160987.6400000006,"y":2551962.6099999994}},{"attributes":{"ID":266411,"DIS_CODE":0,"TOWNNAME":"南區","LI":"明興里","LIN":"3鄰","STREET":"金華路","SECT":"一段","MAREA":" ","LANE":" ","ALLEY":" ","HOUSE_NO":"２１０號","E_COORD97":166960.73000000001,"N_COORD97":2540802.9100000001,"ADDRESS":"金華路一段２１０號","OBJECTID":266407},"geometry":{"x":166960.73000000045,"y":2540802.9100000001}},{"attributes":{"ID":266412,"DIS_CODE":0,"TOWNNAME":"南區","LI":"明興里","LIN":"3鄰","STREET":"金華路","SECT":"一段","MAREA":" ","LANE":" ","ALLEY":" ","HOUSE_NO":"２１２號","E_COORD97":166960.14000000001,"N_COORD97":2540807.4100000001,"ADDRESS":"金華路一段２１２號","OBJECTID":266408},"geometry":{"x":166960.13999999966,"y":2540807.4100000039}},{"attributes":{"ID":266413,"DIS_CODE":0,"TOWNNAME":"北區","LI":"大山里","LIN":"3鄰","STREET":"和緯路","SECT":"一段","MAREA":" ","LANE":" ","ALLEY":" ","HOUSE_NO":"１０５號","E_COORD97":169456.10000000001,"N_COORD97":2545556.04,"ADDRESS":"和緯路一段１０５號","OBJECTID":266409},"geometry":{"x":169456.09999999963,"y":2545556.040000001}},{"attributes":{"ID":266414,"DIS_CODE":0,"TOWNNAME":"南區","LI":"府南里","LIN":"15鄰","STREET":"金華路","SECT":"一段","MAREA":" ","LANE":" ","ALLEY":" ","HOUSE_NO":"４８６之６號","E_COORD97":167042.31,"N_COORD97":2541555.4399999999,"ADDRESS":"金華路一段４８６之６號","OBJECTID":266410},"geometry":{"x":167042.30999999959,"y":2541555.4399999995}},{"attributes":{"ID":266415,"DIS_CODE":0,"TOWNNAME":"安南區","LI":"城東里","LIN":"14鄰","STREET":"城北路","SECT":" ","MAREA":" ","LANE":"２６８巷","ALLEY":" ","HOUSE_NO":"１９號","E_COORD97":160992.26999999999,"N_COORD97":2551962.9100000001,"ADDRESS":"城北路２６８巷１９號","OBJECTID":266411},"geometry":{"x":160992.26999999955,"y":2551962.910000002}},{"attributes":{"ID":266416,"DIS_CODE":0,"TOWNNAME":"安南區","LI":"城東里","LIN":"14鄰","STREET":"城北路","SECT":" ","MAREA":" ","LANE":"２６８巷","ALLEY":" ","HOUSE_NO":"２１號","E_COORD97":160996.89999999999,"N_COORD97":2551962.46,"ADDRESS":"城北路２６８巷２１號","OBJECTID":266412},"geometry":{"x":160996.9000000013,"y":2551962.4600000046}},{"attributes":{"ID":266417,"DIS_CODE":0,"TOWNNAME":"安南區","LI":"城東里","LIN":"14鄰","STREET":"城北路","SECT":" ","MAREA":" ","LANE":"２６８巷","ALLEY":" ","HOUSE_NO":"２３號","E_COORD97":161001.39000000001,"N_COORD97":2551962.3100000001,"ADDRESS":"城北路２６８巷２３號","OBJECTID":266413},"geometry":{"x":161001.3900000006,"y":2551962.3100000005}},{"attributes":{"ID":266418,"DIS_CODE":0,"TOWNNAME":"安南區","LI":"城東里","LIN":"14鄰","STREET":"城北路","SECT":" ","MAREA":" ","LANE":"２６８巷","ALLEY":" ","HOUSE_NO":"２５號","E_COORD97":161005.72,"N_COORD97":2551962.1600000001,"ADDRESS":"城北路２６８巷２５號","OBJECTID":266414},"geometry":{"x":161005.72000000067,"y":2551962.1600000001}},{"attributes":{"ID":266419,"DIS_CODE":0,"TOWNNAME":"仁德區","LI":"後壁里","LIN":"14鄰","STREET":"德南路","SECT":" ","MAREA":" ","LANE":"１３７巷","ALLEY":" ","HOUSE_NO":"３３號","E_COORD97":173583.10000000001,"N_COORD97":2538695.7599999998,"ADDRESS":"德南路１３７巷３３號","OBJECTID":266415},"geometry":{"x":173583.10000000056,"y":2538695.7599999979}},{"attributes":{"ID":266420,"DIS_CODE":0,"TOWNNAME":"仁德區","LI":"後壁里","LIN":"14鄰","STREET":"德善路","SECT":" ","MAREA":" ","LANE":"１６０巷","ALLEY":" ","HOUSE_NO":"７號","E_COORD97":173609.82000000001,"N_COORD97":2538767.52,"ADDRESS":"德善路１６０巷７號","OBJECTID":266416},"geometry":{"x":173609.8200000003,"y":2538767.5199999996}},{"attributes":{"ID":266421,"DIS_CODE":0,"TOWNNAME":"歸仁區","LI":"後市里","LIN":"39鄰","STREET":"文化街","SECT":"二段","MAREA":" ","LANE":"６３巷","ALLEY":" ","HOUSE_NO":"２號","E_COORD97":177309.79000000001,"N_COORD97":2541121.7599999998,"ADDRESS":"文化街二段６３巷２號","OBJECTID":266417},"geometry":{"x":177309.79000000097,"y":2541121.7600000016}},{"attributes":{"ID":266422,"DIS_CODE":0,"TOWNNAME":"仁德區","LI":"後壁里","LIN":"14鄰","STREET":"德善路","SECT":" ","MAREA":" ","LANE":"１６０巷","ALLEY":" ","HOUSE_NO":"３號","E_COORD97":173600.01999999999,"N_COORD97":2538774.52,"ADDRESS":"德善路１６０巷３號","OBJECTID":266418},"geometry":{"x":173600.02000000142,"y":2538774.5199999996}},{"attributes":{"ID":266423,"DIS_CODE":0,"TOWNNAME":"仁德區","LI":"後壁里","LIN":"14鄰","STREET":"德善路","SECT":" ","MAREA":" ","LANE":"１９８巷","ALLEY":" ","HOUSE_NO":"１２號","E_COORD97":173681.07999999999,"N_COORD97":2538671.9100000001,"ADDRESS":"德善路１９８巷１２號","OBJECTID":266419},"geometry":{"x":173681.08000000007,"y":2538671.910000002}},{"attributes":{"ID":266424,"DIS_CODE":0,"TOWNNAME":"仁德區","LI":"後壁里","LIN":"14鄰","STREET":"德善路","SECT":" ","MAREA":" ","LANE":"１９８巷","ALLEY":" ","HOUSE_NO":"２號","E_COORD97":173717.34,"N_COORD97":2538722.0099999998,"ADDRESS":"德善路１９８巷２號","OBJECTID":266420},"geometry":{"x":173717.34000000078,"y":2538722.0100000016}},{"attributes":{"ID":266425,"DIS_CODE":0,"TOWNNAME":"仁德區","LI":"太子里","LIN":"14鄰","STREET":"長興路","SECT":" ","MAREA":" ","LANE":"８７巷","ALLEY":" ","HOUSE_NO":"１８號","E_COORD97":174055.92999999999,"N_COORD97":2543817.7599999998,"ADDRESS":"長興路８７巷１８號","OBJECTID":266421},"geometry":{"x":174055.93000000063,"y":2543817.7599999998}},{"attributes":{"ID":266426,"DIS_CODE":0,"TOWNNAME":"仁德區","LI":"後壁里","LIN":"14鄰","STREET":"德善路","SECT":" ","MAREA":" ","LANE":"１６０巷","ALLEY":" ","HOUSE_NO":"５號","E_COORD97":173603.32000000001,"N_COORD97":2538772.02,"ADDRESS":"德善路１６０巷５號","OBJECTID":266422},"geometry":{"x":173603.3200000003,"y":2538772.0200000033}},{"attributes":{"ID":266427,"DIS_CODE":0,"TOWNNAME":"仁德區","LI":"太子里","LIN":"14鄰","STREET":"長興路","SECT":" ","MAREA":" ","LANE":"８７巷","ALLEY":" ","HOUSE_NO":"２３號","E_COORD97":174014.07000000001,"N_COORD97":2543787,"ADDRESS":"長興路８７巷２３號","OBJECTID":266423},"geometry":{"x":174014.07000000216,"y":2543787.0000000037}},{"attributes":{"ID":266428,"DIS_CODE":0,"TOWNNAME":"南區","LI":"省躬里","LIN":"13鄰","STREET":"萬年路","SECT":" ","MAREA":" ","LANE":" ","ALLEY":" ","HOUSE_NO":"６５號","E_COORD97":166293.63,"N_COORD97":2537221.1600000001,"ADDRESS":"萬年路６５號","OBJECTID":266424},"geometry":{"x":166293.63000000082,"y":2537221.1600000001}},{"attributes":{"ID":266429,"DIS_CODE":0,"TOWNNAME":"仁德區","LI":"太子里","LIN":"14鄰","STREET":"長興路","SECT":" ","MAREA":" ","LANE":"８７巷","ALLEY":" ","HOUSE_NO":"３４號","E_COORD97":174022.04000000001,"N_COORD97":2543804,"ADDRESS":"長興路８７巷３４號","OBJECTID":266425},"geometry":{"x":174022.04000000004,"y":2543804.0000000037}},{"attributes":{"ID":266430,"DIS_CODE":0,"TOWNNAME":"仁德區","LI":"後壁里","LIN":"14鄰","STREET":"德善路","SECT":" ","MAREA":" ","LANE":"１９８巷","ALLEY":" ","HOUSE_NO":"２之１２號","E_COORD97":173691.54000000001,"N_COORD97":2538718.25,"ADDRESS":"德善路１９８巷２之１２號","OBJECTID":266426},"geometry":{"x":173691.54000000004,"y":2538718.2500000019}},{"attributes":{"ID":266431,"DIS_CODE":0,"TOWNNAME":"仁德區","LI":"後壁里","LIN":"14鄰","STREET":"德善路","SECT":" ","MAREA":" ","LANE":"１９８巷","ALLEY":" ","HOUSE_NO":"２之１５號","E_COORD97":173700.48000000001,"N_COORD97":2538713,"ADDRESS":"德善路１９８巷２之１５號","OBJECTID":266427},"geometry":{"x":173700.48000000045,"y":2538713.0000000019}},{"attributes":{"ID":266432,"DIS_CODE":0,"TOWNNAME":"永康區","LI":"大灣里","LIN":"14鄰","STREET":"大灣路","SECT":" ","MAREA":" ","LANE":"２８８巷","ALLEY":" ","HOUSE_NO":"２１號","E_COORD97":174852.69,"N_COORD97":2545274.5499999998,"ADDRESS":"大灣路２８８巷２１號","OBJECTID":266428},"geometry":{"x":174852.69000000134,"y":2545274.5500000007}},{"attributes":{"ID":266433,"DIS_CODE":0,"TOWNNAME":"歸仁區","LI":"南保里","LIN":"35鄰","STREET":"中山路","SECT":"三段","MAREA":" ","LANE":"１００巷","ALLEY":" ","HOUSE_NO":"２７號","E_COORD97":176706.39999999999,"N_COORD97":2540963.6099999999,"ADDRESS":"中山路三段１００巷２７號","OBJECTID":266429},"geometry":{"x":176706.4000000013,"y":2540963.6099999994}},{"attributes":{"ID":266434,"DIS_CODE":0,"TOWNNAME":"永康區","LI":"大灣里","LIN":"14鄰","STREET":"大灣路","SECT":" ","MAREA":" ","LANE":"２８８巷","ALLEY":" ","HOUSE_NO":"１１號","E_COORD97":174877.67999999999,"N_COORD97":2545260.7400000002,"ADDRESS":"大灣路２８８巷１１號","OBJECTID":266430},"geometry":{"x":174877.68000000063,"y":2545260.7400000021}},{"attributes":{"ID":266435,"DIS_CODE":0,"TOWNNAME":"永康區","LI":"中興里","LIN":"14鄰","STREET":"中興街","SECT":" ","MAREA":" ","LANE":"６９巷","ALLEY":" ","HOUSE_NO":"３３號","E_COORD97":171961.57000000001,"N_COORD97":2545287.2799999998,"ADDRESS":"中興街６９巷３３號","OBJECTID":266431},"geometry":{"x":171961.57000000123,"y":2545287.2800000012}},{"attributes":{"ID":266436,"DIS_CODE":0,"TOWNNAME":"永康區","LI":"大灣里","LIN":"14鄰","STREET":"大灣路","SECT":" ","MAREA":" ","LANE":"２８８巷","ALLEY":" ","HOUSE_NO":"１號","E_COORD97":174900.07999999999,"N_COORD97":2545250.4900000002,"ADDRESS":"大灣路２８８巷１號","OBJECTID":266432},"geometry":{"x":174900.08000000007,"y":2545250.4900000002}},{"attributes":{"ID":266437,"DIS_CODE":0,"TOWNNAME":"永康區","LI":"大灣里","LIN":"14鄰","STREET":"大灣路","SECT":" ","MAREA":" ","LANE":"２８８巷","ALLEY":" ","HOUSE_NO":"９號","E_COORD97":174882.29000000001,"N_COORD97":2545258.2400000002,"ADDRESS":"大灣路２８８巷９號","OBJECTID":266433},"geometry":{"x":174882.29000000097,"y":2545258.2400000021}},{"attributes":{"ID":266438,"DIS_CODE":0,"TOWNNAME":"永康區","LI":"大灣里","LIN":"14鄰","STREET":"大灣路","SECT":" ","MAREA":" ","LANE":"２８８巷","ALLEY":" ","HOUSE_NO":"３號","E_COORD97":174895.42999999999,"N_COORD97":2545252.7400000002,"ADDRESS":"大灣路２８８巷３號","OBJECTID":266434},"geometry":{"x":174895.4299999997,"y":2545252.7400000002}},{"attributes":{"ID":266439,"DIS_CODE":0,"TOWNNAME":"永康區","LI":"中興里","LIN":"14鄰","STREET":"中興街","SECT":" ","MAREA":" ","LANE":"６９巷","ALLEY":" ","HOUSE_NO":"３號","E_COORD97":172040.62,"N_COORD97":2545287.5,"ADDRESS":"中興街６９巷３號","OBJECTID":266435},"geometry":{"x":172040.62000000104,"y":2545287.5}},{"attributes":{"ID":266440,"DIS_CODE":0,"TOWNNAME":"永康區","LI":"崑山里","LIN":"14鄰","STREET":"大灣路","SECT":" ","MAREA":" ","LANE":"９７０巷","ALLEY":" ","HOUSE_NO":"２９號","E_COORD97":173544.70999999999,"N_COORD97":2544488.9700000002,"ADDRESS":"大灣路９７０巷２９號","OBJECTID":266436},"geometry":{"x":173544.70999999996,"y":2544488.9700000007}},{"attributes":{"ID":266441,"DIS_CODE":0,"TOWNNAME":"安南區","LI":"總頭里","LIN":"9鄰","STREET":"長溪路","SECT":"二段","MAREA":" ","LANE":"５８１巷","ALLEY":" ","HOUSE_NO":"２２之１號","E_COORD97":168141.862501,"N_COORD97":2550690.4722199999,"ADDRESS":"長溪路二段５８１巷２２之１號","OBJECTID":266437},"geometry":{"x":168141.86250100099,"y":2550690.4722210001}},{"attributes":{"ID":266442,"DIS_CODE":0,"TOWNNAME":"永康區","LI":"崑山里","LIN":"14鄰","STREET":"大灣路","SECT":" ","MAREA":" ","LANE":"９７０巷","ALLEY":" ","HOUSE_NO":"２５號","E_COORD97":173543.69,"N_COORD97":2544480.23,"ADDRESS":"大灣路９７０巷２５號","OBJECTID":266438},"geometry":{"x":173543.68999999948,"y":2544480.2300000004}},{"attributes":{"ID":266443,"DIS_CODE":0,"TOWNNAME":"安南區","LI":"溪東里","LIN":"14鄰","STREET":"北安路","SECT":"二段","MAREA":" ","LANE":"９３巷","ALLEY":" ","HOUSE_NO":"１１號","E_COORD97":168432.60999999999,"N_COORD97":2547434.4199999999,"ADDRESS":"北安路二段９３巷１１號","OBJECTID":266439},"geometry":{"x":168432.61000000034,"y":2547434.4199999999}},{"attributes":{"ID":266444,"DIS_CODE":0,"TOWNNAME":"安南區","LI":"溪東里","LIN":"14鄰","STREET":"北安路","SECT":"二段","MAREA":" ","LANE":"９３巷","ALLEY":" ","HOUSE_NO":"１２號","E_COORD97":168429.75,"N_COORD97":2547455.96,"ADDRESS":"北安路二段９３巷１２號","OBJECTID":266440},"geometry":{"x":168429.75,"y":2547455.9600000009}},{"attributes":{"ID":266445,"DIS_CODE":0,"TOWNNAME":"安南區","LI":"溪東里","LIN":"14鄰","STREET":"北安路","SECT":"二段","MAREA":" ","LANE":"９３巷","ALLEY":" ","HOUSE_NO":"６８號","E_COORD97":168238.32000000001,"N_COORD97":2547436.2000000002,"ADDRESS":"北安路二段９３巷６８號","OBJECTID":266441},"geometry":{"x":168238.3200000003,"y":2547436.200000003}},{"attributes":{"ID":266446,"DIS_CODE":0,"TOWNNAME":"永康區","LI":"三民里","LIN":"14鄰","STREET":"和平路","SECT":" ","MAREA":" ","LANE":"２０６巷","ALLEY":" ","HOUSE_NO":"２６號","E_COORD97":175004.97,"N_COORD97":2550574.1800000002,"ADDRESS":"和平路２０６巷２６號","OBJECTID":266442},"geometry":{"x":175004.97000000067,"y":2550574.1800000016}},{"attributes":{"ID":266447,"DIS_CODE":0,"TOWNNAME":"東區","LI":"德高里","LIN":"14鄰","STREET":"仁和路","SECT":" ","MAREA":" ","LANE":"１６５巷","ALLEY":" ","HOUSE_NO":"１０號","E_COORD97":171646.72,"N_COORD97":2540911.7400000002,"ADDRESS":"仁和路１６５巷１０號","OBJECTID":266443},"geometry":{"x":171646.72000000067,"y":2540911.7400000021}},{"attributes":{"ID":266448,"DIS_CODE":0,"TOWNNAME":"東區","LI":"德高里","LIN":"14鄰","STREET":"仁和路","SECT":" ","MAREA":" ","LANE":"１６５巷","ALLEY":" ","HOUSE_NO":"１２號","E_COORD97":171651.85000000001,"N_COORD97":2540913.9399999999,"ADDRESS":"仁和路１６５巷１２號","OBJECTID":266444},"geometry":{"x":171651.85000000149,"y":2540913.9399999995}},{"attributes":{"ID":266449,"DIS_CODE":0,"TOWNNAME":"東區","LI":"德高里","LIN":"14鄰","STREET":"城東街","SECT":" ","MAREA":" ","LANE":"９９巷","ALLEY":" ","HOUSE_NO":"１號","E_COORD97":171702.38,"N_COORD97":2540834.8999999999,"ADDRESS":"城東街９９巷１號","OBJECTID":266445},"geometry":{"x":171702.37999999989,"y":2540834.9000000041}},{"attributes":{"ID":266450,"DIS_CODE":0,"TOWNNAME":"東區","LI":"德高里","LIN":"14鄰","STREET":"城東街","SECT":" ","MAREA":" ","LANE":"９９巷","ALLEY":" ","HOUSE_NO":"３號","E_COORD97":171700.70000000001,"N_COORD97":2540838.7999999998,"ADDRESS":"城東街９９巷３號","OBJECTID":266446},"geometry":{"x":171700.70000000019,"y":2540838.8000000007}},{"attributes":{"ID":266451,"DIS_CODE":0,"TOWNNAME":"東區","LI":"德高里","LIN":"14鄰","STREET":"仁和路","SECT":" ","MAREA":" ","LANE":"１６５巷","ALLEY":" ","HOUSE_NO":"８號","E_COORD97":171641.76999999999,"N_COORD97":2540909,"ADDRESS":"仁和路１６５巷８號","OBJECTID":266447},"geometry":{"x":171641.76999999955,"y":2540909.0000000019}},{"attributes":{"ID":266452,"DIS_CODE":0,"TOWNNAME":"東區","LI":"德高里","LIN":"14鄰","STREET":"仁和路","SECT":" ","MAREA":" ","LANE":"１９９巷","ALLEY":" ","HOUSE_NO":"１號","E_COORD97":171655.60999999999,"N_COORD97":2540854.79,"ADDRESS":"仁和路１９９巷１號","OBJECTID":266448},"geometry":{"x":171655.61000000034,"y":2540854.7900000028}},{"attributes":{"ID":266453,"DIS_CODE":0,"TOWNNAME":"東區","LI":"德高里","LIN":"14鄰","STREET":"仁和路","SECT":" ","MAREA":" ","LANE":"１９９巷","ALLEY":" ","HOUSE_NO":"３號","E_COORD97":171668.76999999999,"N_COORD97":2540860.4900000002,"ADDRESS":"仁和路１９９巷３號","OBJECTID":266449},"geometry":{"x":171668.76999999955,"y":2540860.4900000002}},{"attributes":{"ID":266454,"DIS_CODE":0,"TOWNNAME":"中西區","LI":"萬昌里","LIN":"14鄰","STREET":"民權路","SECT":"一段","MAREA":" ","LANE":"９０巷","ALLEY":" ","HOUSE_NO":"１１號","E_COORD97":168991.59,"N_COORD97":2543457.5099999998,"ADDRESS":"民權路一段９０巷１１號","OBJECTID":266450},"geometry":{"x":168991.58999999985,"y":2543457.5099999979}},{"attributes":{"ID":266455,"DIS_CODE":0,"TOWNNAME":"中西區","LI":"萬昌里","LIN":"14鄰","STREET":"民權路","SECT":"一段","MAREA":" ","LANE":"９０巷","ALLEY":" ","HOUSE_NO":"１號","E_COORD97":168979.92999999999,"N_COORD97":2543436.27,"ADDRESS":"民權路一段９０巷１號","OBJECTID":266451},"geometry":{"x":168979.93000000063,"y":2543436.2700000014}},{"attributes":{"ID":266456,"DIS_CODE":0,"TOWNNAME":"東區","LI":"忠孝里","LIN":"37鄰","STREET":"榮譽街","SECT":" ","MAREA":" ","LANE":"１３０巷","ALLEY":" ","HOUSE_NO":"７號","E_COORD97":169920.20000000001,"N_COORD97":2541735.2400000002,"ADDRESS":"榮譽街１３０巷７號","OBJECTID":266452},"geometry":{"x":169920.20000000019,"y":2541735.2400000021}},{"attributes":{"ID":266457,"DIS_CODE":0,"TOWNNAME":"東區","LI":"忠孝里","LIN":"37鄰","STREET":"榮譽街","SECT":" ","MAREA":" ","LANE":" ","ALLEY":" ","HOUSE_NO":"１３２號","E_COORD97":169895.32000000001,"N_COORD97":2541761.2200000002,"ADDRESS":"榮譽街１３２號","OBJECTID":266453},"geometry":{"x":169895.32000000123,"y":2541761.2200000007}},{"attributes":{"ID":266458,"DIS_CODE":0,"TOWNNAME":"東區","LI":"忠孝里","LIN":"37鄰","STREET":"榮譽街","SECT":" ","MAREA":" ","LANE":" ","ALLEY":" ","HOUSE_NO":"１３２號之１","E_COORD97":169898.56,"N_COORD97":2541763.3300000001,"ADDRESS":"榮譽街１３２號之１","OBJECTID":266454},"geometry":{"x":169898.55999999959,"y":2541763.3300000001}},{"attributes":{"ID":266459,"DIS_CODE":0,"TOWNNAME":"東區","LI":"忠孝里","LIN":"37鄰","STREET":"榮譽街","SECT":" ","MAREA":" ","LANE":" ","ALLEY":" ","HOUSE_NO":"１３２號之２","E_COORD97":169903.10000000001,"N_COORD97":2541766.0800000001,"ADDRESS":"榮譽街１３２號之２","OBJECTID":266455},"geometry":{"x":169903.10000000056,"y":2541766.0800000019}},{"attributes":{"ID":266460,"DIS_CODE":0,"TOWNNAME":"北區","LI":"振興里","LIN":"3鄰","STREET":"開元路","SECT":" ","MAREA":" ","LANE":" ","ALLEY":" ","HOUSE_NO":"１５２號","E_COORD97":170001.91,"N_COORD97":2545262.4900000002,"ADDRESS":"開元路１５２號","OBJECTID":266456},"geometry":{"x":170001.91000000015,"y":2545262.4900000021}},{"attributes":{"ID":266461,"DIS_CODE":0,"TOWNNAME":"北區","LI":"振興里","LIN":"3鄰","STREET":"開元路","SECT":" ","MAREA":" ","LANE":" ","ALLEY":" ","HOUSE_NO":"１５４號","E_COORD97":170008.07999999999,"N_COORD97":2545260.79,"ADDRESS":"開元路１５４號","OBJECTID":266457},"geometry":{"x":170008.08000000194,"y":2545260.7899999991}},{"attributes":{"ID":266462,"DIS_CODE":0,"TOWNNAME":"北區","LI":"振興里","LIN":"3鄰","STREET":"開元路","SECT":" ","MAREA":" ","LANE":" ","ALLEY":" ","HOUSE_NO":"１５６號","E_COORD97":170013.39000000001,"N_COORD97":2545261.5499999998,"ADDRESS":"開元路１５６號","OBJECTID":266458},"geometry":{"x":170013.38999999966,"y":2545261.5500000007}},{"attributes":{"ID":266463,"DIS_CODE":0,"TOWNNAME":"北區","LI":"振興里","LIN":"3鄰","STREET":"開元路","SECT":" ","MAREA":" ","LANE":" ","ALLEY":" ","HOUSE_NO":"１５８號","E_COORD97":170018.14999999999,"N_COORD97":2545262.52,"ADDRESS":"開元路１５８號","OBJECTID":266459},"geometry":{"x":170018.15000000224,"y":2545262.5200000014}},{"attributes":{"ID":266464,"DIS_CODE":0,"TOWNNAME":"北區","LI":"振興里","LIN":"3鄰","STREET":"開元路","SECT":" ","MAREA":" ","LANE":" ","ALLEY":" ","HOUSE_NO":"１６０號","E_COORD97":170022.59,"N_COORD97":2545264.0299999998,"ADDRESS":"開元路１６０號","OBJECTID":266460},"geometry":{"x":170022.58999999985,"y":2545264.0299999975}},{"attributes":{"ID":266465,"DIS_CODE":0,"TOWNNAME":"北區","LI":"振興里","LIN":"3鄰","STREET":"開元路","SECT":" ","MAREA":" ","LANE":" ","ALLEY":" ","HOUSE_NO":"１６２號","E_COORD97":170027.25,"N_COORD97":2545265.7599999998,"ADDRESS":"開元路１６２號","OBJECTID":266461},"geometry":{"x":170027.25000000186,"y":2545265.7599999998}},{"attributes":{"ID":266466,"DIS_CODE":0,"TOWNNAME":"南區","LI":"省躬里","LIN":"13鄰","STREET":"萬年路","SECT":" ","MAREA":" ","LANE":" ","ALLEY":" ","HOUSE_NO":"７１號","E_COORD97":166299.03,"N_COORD97":2537223.3799999999,"ADDRESS":"萬年路７１號","OBJECTID":266462},"geometry":{"x":166299.03000000026,"y":2537223.3800000008}},{"attributes":{"ID":266467,"DIS_CODE":0,"TOWNNAME":"南區","LI":"南都里","LIN":"9鄰","STREET":"中華南路","SECT":"二段","MAREA":" ","LANE":" ","ALLEY":" ","HOUSE_NO":"２４７之２號","E_COORD97":166657.95000000001,"N_COORD97":2540175.0099999998,"ADDRESS":"中華南路二段２４７之２號","OBJECTID":266463},"geometry":{"x":166657.95000000112,"y":2540175.0099999998}},{"attributes":{"ID":266468,"DIS_CODE":0,"TOWNNAME":"北區","LI":"和順里","LIN":"3鄰","STREET":"西門路","SECT":"三段","MAREA":" ","LANE":" ","ALLEY":" ","HOUSE_NO":"５５號","E_COORD97":168275.35999999999,"N_COORD97":2544722.0299999998,"ADDRESS":"西門路三段５５號","OBJECTID":266464},"geometry":{"x":168275.36000000034,"y":2544722.0300000012}},{"attributes":{"ID":266469,"DIS_CODE":0,"TOWNNAME":"北區","LI":"和順里","LIN":"3鄰","STREET":"西門路","SECT":"三段","MAREA":" ","LANE":" ","ALLEY":" ","HOUSE_NO":"６７號","E_COORD97":168288.70000000001,"N_COORD97":2544738.48,"ADDRESS":"西門路三段６７號","OBJECTID":266465},"geometry":{"x":168288.70000000112,"y":2544738.4800000023}},{"attributes":{"ID":266470,"DIS_CODE":0,"TOWNNAME":"東區","LI":"忠孝里","LIN":"38鄰","STREET":"榮譽街","SECT":" ","MAREA":" ","LANE":" ","ALLEY":" ","HOUSE_NO":"１３４號","E_COORD97":169920.53,"N_COORD97":2541772.9500000002,"ADDRESS":"榮譽街１３４號","OBJECTID":266466},"geometry":{"x":169920.53000000212,"y":2541772.9500000011}},{"attributes":{"ID":266471,"DIS_CODE":0,"TOWNNAME":"東區","LI":"忠孝里","LIN":"38鄰","STREET":"榮譽街","SECT":" ","MAREA":" ","LANE":" ","ALLEY":" ","HOUSE_NO":"１４６號","E_COORD97":169933.07999999999,"N_COORD97":2541785.2000000002,"ADDRESS":"榮譽街１４６號","OBJECTID":266467},"geometry":{"x":169933.08000000007,"y":2541785.2000000011}},{"attributes":{"ID":266472,"DIS_CODE":0,"TOWNNAME":"中西區","LI":"萬昌里","LIN":"14鄰","STREET":"民權路","SECT":"一段","MAREA":" ","LANE":"９０巷","ALLEY":" ","HOUSE_NO":"３號","E_COORD97":168982.32000000001,"N_COORD97":2543442.4300000002,"ADDRESS":"民權路一段９０巷３號","OBJECTID":266468},"geometry":{"x":168982.3200000003,"y":2543442.4300000016}},{"attributes":{"ID":266473,"DIS_CODE":0,"TOWNNAME":"中西區","LI":"萬昌里","LIN":"14鄰","STREET":"民權路","SECT":"一段","MAREA":" ","LANE":"９０巷","ALLEY":" ","HOUSE_NO":"５號","E_COORD97":168986.03,"N_COORD97":2543445.0699999998,"ADDRESS":"民權路一段９０巷５號","OBJECTID":266469},"geometry":{"x":168986.03000000026,"y":2543445.0700000022}},{"attributes":{"ID":266474,"DIS_CODE":0,"TOWNNAME":"中西區","LI":"萬昌里","LIN":"14鄰","STREET":"民權路","SECT":"一段","MAREA":" ","LANE":"９０巷","ALLEY":" ","HOUSE_NO":"７號","E_COORD97":168987.75,"N_COORD97":2543450.8900000001,"ADDRESS":"民權路一段９０巷７號","OBJECTID":266470},"geometry":{"x":168987.75,"y":2543450.8900000025}},{"attributes":{"ID":266475,"DIS_CODE":0,"TOWNNAME":"中西區","LI":"萬昌里","LIN":"14鄰","STREET":"民權路","SECT":"一段","MAREA":" ","LANE":"９０巷","ALLEY":" ","HOUSE_NO":"９號","E_COORD97":168989.73999999999,"N_COORD97":2543454.6000000001,"ADDRESS":"民權路一段９０巷９號","OBJECTID":266471},"geometry":{"x":168989.74000000022,"y":2543454.6000000015}},{"attributes":{"ID":266476,"DIS_CODE":0,"TOWNNAME":"中西區","LI":"福安里","LIN":"14鄰","STREET":"友愛街","SECT":" ","MAREA":" ","LANE":"１１５巷","ALLEY":" ","HOUSE_NO":"１１號","E_COORD97":167926.85999999999,"N_COORD97":2543475.1699999999,"ADDRESS":"友愛街１１５巷１１號","OBJECTID":266472},"geometry":{"x":167926.86000000127,"y":2543475.1700000018}},{"attributes":{"ID":266477,"DIS_CODE":0,"TOWNNAME":"東區","LI":"忠孝里","LIN":"12鄰","STREET":"榮譽街","SECT":" ","MAREA":" ","LANE":" ","ALLEY":" ","HOUSE_NO":"６７號","E_COORD97":169727.57999999999,"N_COORD97":2541707.04,"ADDRESS":"榮譽街６７號","OBJECTID":266473},"geometry":{"x":169727.58000000007,"y":2541707.0399999991}},{"attributes":{"ID":266478,"DIS_CODE":0,"TOWNNAME":"東區","LI":"忠孝里","LIN":"12鄰","STREET":"榮譽街","SECT":" ","MAREA":" ","LANE":" ","ALLEY":" ","HOUSE_NO":"６７號之１","E_COORD97":169785.26000000001,"N_COORD97":2541813.0899999999,"ADDRESS":"榮譽街６７號之１","OBJECTID":266474},"geometry":{"x":169785.26000000071,"y":2541813.0900000036}},{"attributes":{"ID":266479,"DIS_CODE":0,"TOWNNAME":"中西區","LI":"福安里","LIN":"14鄰","STREET":"友愛街","SECT":" ","MAREA":" ","LANE":"１１５巷","ALLEY":" ","HOUSE_NO":"１３號","E_COORD97":167925.25,"N_COORD97":2543469.7999999998,"ADDRESS":"友愛街１１５巷１３號","OBJECTID":266475},"geometry":{"x":167925.25000000186,"y":2543469.8000000007}},{"attributes":{"ID":266480,"DIS_CODE":0,"TOWNNAME":"中西區","LI":"福安里","LIN":"14鄰","STREET":"友愛街","SECT":" ","MAREA":" ","LANE":"１１５巷","ALLEY":" ","HOUSE_NO":"１５號","E_COORD97":167923.45999999999,"N_COORD97":2543465.3199999998,"ADDRESS":"友愛街１１５巷１５號","OBJECTID":266476},"geometry":{"x":167923.45999999996,"y":2543465.3200000003}},{"attributes":{"ID":266481,"DIS_CODE":0,"TOWNNAME":"中西區","LI":"福安里","LIN":"14鄰","STREET":"友愛街","SECT":" ","MAREA":" ","LANE":"１１５巷","ALLEY":" ","HOUSE_NO":"１７號","E_COORD97":167922.56,"N_COORD97":2543461.7400000002,"ADDRESS":"友愛街１１５巷１７號","OBJECTID":266477},"geometry":{"x":167922.56000000145,"y":2543461.7400000021}},{"attributes":{"ID":266482,"DIS_CODE":0,"TOWNNAME":"中西區","LI":"福安里","LIN":"14鄰","STREET":"友愛街","SECT":" ","MAREA":" ","LANE":"１１５巷","ALLEY":" ","HOUSE_NO":"３號","E_COORD97":167938.85000000001,"N_COORD97":2543500.3399999999,"ADDRESS":"友愛街１１５巷３號","OBJECTID":266478},"geometry":{"x":167938.84999999963,"y":2543500.3400000017}},{"attributes":{"ID":266483,"DIS_CODE":0,"TOWNNAME":"中西區","LI":"福安里","LIN":"14鄰","STREET":"友愛街","SECT":" ","MAREA":" ","LANE":"１１５巷","ALLEY":" ","HOUSE_NO":"５號","E_COORD97":167937.78,"N_COORD97":2543493.0299999998,"ADDRESS":"友愛街１１５巷５號","OBJECTID":266479},"geometry":{"x":167937.78000000119,"y":2543493.0299999993}},{"attributes":{"ID":266484,"DIS_CODE":0,"TOWNNAME":"中西區","LI":"福安里","LIN":"14鄰","STREET":"友愛街","SECT":" ","MAREA":" ","LANE":"１１５巷","ALLEY":" ","HOUSE_NO":"７號","E_COORD97":167930.47,"N_COORD97":2543486.3900000001,"ADDRESS":"友愛街１１５巷７號","OBJECTID":266480},"geometry":{"x":167930.47000000067,"y":2543486.3899999987}},{"attributes":{"ID":266485,"DIS_CODE":0,"TOWNNAME":"中西區","LI":"福安里","LIN":"14鄰","STREET":"友愛街","SECT":" ","MAREA":" ","LANE":"１１５巷","ALLEY":" ","HOUSE_NO":"９號","E_COORD97":167929.01000000001,"N_COORD97":2543480.7200000002,"ADDRESS":"友愛街１１５巷９號","OBJECTID":266481},"geometry":{"x":167929.01000000071,"y":2543480.7200000007}},{"attributes":{"ID":266486,"DIS_CODE":0,"TOWNNAME":"安南區","LI":"溪頂里","LIN":"14鄰","STREET":"惠安街","SECT":" ","MAREA":" ","LANE":"１６１巷","ALLEY":" ","HOUSE_NO":"８號","E_COORD97":168765.67999999999,"N_COORD97":2547323.8599999999,"ADDRESS":"惠安街１６１巷８號","OBJECTID":266482},"geometry":{"x":168765.6799999997,"y":2547323.8600000013}},{"attributes":{"ID":266487,"DIS_CODE":0,"TOWNNAME":"安南區","LI":"溪頂里","LIN":"14鄰","STREET":"惠安街","SECT":" ","MAREA":" ","LANE":"１６１巷","ALLEY":" ","HOUSE_NO":"６３號","E_COORD97":169005.66,"N_COORD97":2547352.9399999999,"ADDRESS":"惠安街１６１巷６３號","OBJECTID":266483},"geometry":{"x":169005.66000000201,"y":2547352.9399999995}},{"attributes":{"ID":266488,"DIS_CODE":0,"TOWNNAME":"安南區","LI":"學東里","LIN":"14鄰","STREET":"公學路","SECT":"七段","MAREA":" ","LANE":"９７巷","ALLEY":" ","HOUSE_NO":"２０號","E_COORD97":161735.13,"N_COORD97":2553345.9399999999,"ADDRESS":"公學路七段９７巷２０號","OBJECTID":266484},"geometry":{"x":161735.13000000082,"y":2553345.9400000013}},{"attributes":{"ID":266489,"DIS_CODE":0,"TOWNNAME":"東區","LI":"忠孝里","LIN":"12鄰","STREET":"榮譽街","SECT":" ","MAREA":" ","LANE":" ","ALLEY":" ","HOUSE_NO":"６７號之２","E_COORD97":169788.19,"N_COORD97":2541813.8399999999,"ADDRESS":"榮譽街６７號之２","OBJECTID":266485},"geometry":{"x":169788.19000000041,"y":2541813.8399999999}},{"attributes":{"ID":266490,"DIS_CODE":0,"TOWNNAME":"六甲區","LI":"中社里","LIN":"3鄰","STREET":" ","SECT":" ","MAREA":"中社","LANE":" ","ALLEY":" ","HOUSE_NO":"７５號","E_COORD97":181162.98000000001,"N_COORD97":2570795.25,"ADDRESS":"中社７５號","OBJECTID":266486},"geometry":{"x":181162.98000000045,"y":2570795.25}},{"attributes":{"ID":266491,"DIS_CODE":0,"TOWNNAME":"北區","LI":"安民里","LIN":"3鄰","STREET":"國華街","SECT":"四段","MAREA":" ","LANE":" ","ALLEY":" ","HOUSE_NO":"３９號","E_COORD97":168024.57000000001,"N_COORD97":2544674.21,"ADDRESS":"國華街四段３９號","OBJECTID":266487},"geometry":{"x":168024.5700000003,"y":2544674.2100000009}},{"attributes":{"ID":266492,"DIS_CODE":0,"TOWNNAME":"安南區","LI":"學東里","LIN":"14鄰","STREET":"公學路","SECT":"七段","MAREA":" ","LANE":"９７巷","ALLEY":" ","HOUSE_NO":"３０號","E_COORD97":161730.14000000001,"N_COORD97":2553323.7599999998,"ADDRESS":"公學路七段９７巷３０號","OBJECTID":266488},"geometry":{"x":161730.1400000006,"y":2553323.7599999998}},{"attributes":{"ID":266493,"DIS_CODE":0,"TOWNNAME":"安南區","LI":"學東里","LIN":"14鄰","STREET":"公學路","SECT":"七段","MAREA":" ","LANE":"９７巷","ALLEY":" ","HOUSE_NO":"３２號","E_COORD97":161729.92000000001,"N_COORD97":2553319.2400000002,"ADDRESS":"公學路七段９７巷３２號","OBJECTID":266489},"geometry":{"x":161729.92000000086,"y":2553319.2400000039}},{"attributes":{"ID":266494,"DIS_CODE":0,"TOWNNAME":"永康區","LI":"復國里","LIN":"14鄰","STREET":"復國二路","SECT":" ","MAREA":" ","LANE":"１７８巷","ALLEY":" ","HOUSE_NO":"８號之１０","E_COORD97":172949.26000000001,"N_COORD97":2545644.1099999999,"ADDRESS":"復國二路１７８巷８號之１０","OBJECTID":266490},"geometry":{"x":172949.25999999885,"y":2545644.1100000013}},{"attributes":{"ID":266495,"DIS_CODE":0,"TOWNNAME":"永康區","LI":"中華里","LIN":"14鄰","STREET":"忠義街","SECT":" ","MAREA":" ","LANE":"４４巷","ALLEY":" ","HOUSE_NO":"１４號","E_COORD97":171761.04999999999,"N_COORD97":2544462.8500000001,"ADDRESS":"忠義街４４巷１４號","OBJECTID":266491},"geometry":{"x":171761.05000000075,"y":2544462.8500000015}},{"attributes":{"ID":266496,"DIS_CODE":0,"TOWNNAME":"永康區","LI":"\u25A0洲里","LIN":"14鄰","STREET":"中正南路","SECT":" ","MAREA":" ","LANE":"７７９巷","ALLEY":" ","HOUSE_NO":"２６號","E_COORD97":171612.29999999999,"N_COORD97":2549010.75,"ADDRESS":"中正南路７７９巷２６號","OBJECTID":266492},"geometry":{"x":171612.30000000075,"y":2549010.7500000019}},{"attributes":{"ID":266497,"DIS_CODE":0,"TOWNNAME":"永康區","LI":"龍潭里","LIN":"14鄰","STREET":"龍埔街","SECT":" ","MAREA":" ","LANE":"７８巷","ALLEY":" ","HOUSE_NO":"１３號","E_COORD97":174624.28,"N_COORD97":2548309.3300000001,"ADDRESS":"龍埔街７８巷１３號","OBJECTID":266493},"geometry":{"x":174624.28000000026,"y":2548309.3300000001}},{"attributes":{"ID":266498,"DIS_CODE":0,"TOWNNAME":"安南區","LI":"安順里","LIN":"14鄰","STREET":"總安街","SECT":"一段","MAREA":" ","LANE":"１４６巷","ALLEY":" ","HOUSE_NO":"９６號","E_COORD97":169631.76999999999,"N_COORD97":2550398.46,"ADDRESS":"總安街一段１４６巷９６號","OBJECTID":266494},"geometry":{"x":169631.77000000048,"y":2550398.4600000009}},{"attributes":{"ID":266499,"DIS_CODE":0,"TOWNNAME":"安南區","LI":"安順里","LIN":"14鄰","STREET":"總安街","SECT":"一段","MAREA":" ","LANE":"１４６巷","ALLEY":" ","HOUSE_NO":"９８號","E_COORD97":169632.09,"N_COORD97":2550403.0699999998,"ADDRESS":"總安街一段１４６巷９８號","OBJECTID":266495},"geometry":{"x":169632.09000000078,"y":2550403.0700000022}},{"attributes":{"ID":266500,"DIS_CODE":0,"TOWNNAME":"安南區","LI":"安順里","LIN":"14鄰","STREET":"總安街","SECT":"一段","MAREA":" ","LANE":"１４６巷","ALLEY":" ","HOUSE_NO":"１００號","E_COORD97":169632.73000000001,"N_COORD97":2550407.3500000001,"ADDRESS":"總安街一段１４６巷１００號","OBJECTID":266496},"geometry":{"x":169632.73000000231,"y":2550407.3499999996}},{"attributes":{"ID":266501,"DIS_CODE":0,"TOWNNAME":"安南區","LI":"安順里","LIN":"14鄰","STREET":"總安街","SECT":"一段","MAREA":" ","LANE":"１４６巷","ALLEY":" ","HOUSE_NO":"１０２號","E_COORD97":169633.20000000001,"N_COORD97":2550411.1600000001,"ADDRESS":"總安街一段１４６巷１０２號","OBJECTID":266497},"geometry":{"x":169633.20000000112,"y":2550411.160000002}},{"attributes":{"ID":266502,"DIS_CODE":0,"TOWNNAME":"安南區","LI":"安順里","LIN":"14鄰","STREET":"總安街","SECT":"一段","MAREA":" ","LANE":"１４６巷","ALLEY":" ","HOUSE_NO":"１０６號","E_COORD97":169633.84,"N_COORD97":2550415.29,"ADDRESS":"總安街一段１４６巷１０６號","OBJECTID":266498},"geometry":{"x":169633.84000000078,"y":2550415.2899999991}},{"attributes":{"ID":266503,"DIS_CODE":0,"TOWNNAME":"安南區","LI":"安順里","LIN":"14鄰","STREET":"總安街","SECT":"一段","MAREA":" ","LANE":"１４６巷","ALLEY":" ","HOUSE_NO":"１０８號","E_COORD97":169634.31,"N_COORD97":2550419.8999999999,"ADDRESS":"總安街一段１４６巷１０８號","OBJECTID":266499},"geometry":{"x":169634.30999999959,"y":2550419.9000000022}},{"attributes":{"ID":266504,"DIS_CODE":0,"TOWNNAME":"安南區","LI":"安順里","LIN":"14鄰","STREET":"總安街","SECT":"一段","MAREA":" ","LANE":"１４６巷","ALLEY":" ","HOUSE_NO":"１１０號","E_COORD97":169634.31,"N_COORD97":2550423.71,"ADDRESS":"總安街一段１４６巷１１０號","OBJECTID":266500},"geometry":{"x":169634.30999999959,"y":2550423.7100000009}},{"attributes":{"ID":266505,"DIS_CODE":0,"TOWNNAME":"安南區","LI":"安順里","LIN":"14鄰","STREET":"總安街","SECT":"一段","MAREA":" ","LANE":"１４６巷","ALLEY":" ","HOUSE_NO":"１１２號","E_COORD97":169634.79000000001,"N_COORD97":2550428.4700000002,"ADDRESS":"總安街一段１４６巷１１２號","OBJECTID":266501},"geometry":{"x":169634.79000000004,"y":2550428.4700000007}},{"attributes":{"ID":266506,"DIS_CODE":0,"TOWNNAME":"安南區","LI":"安順里","LIN":"14鄰","STREET":"總安街","SECT":"一段","MAREA":" ","LANE":"１４６巷","ALLEY":" ","HOUSE_NO":"１１６號","E_COORD97":169635.42000000001,"N_COORD97":2550432.1200000001,"ADDRESS":"總安街一段１４６巷１１６號","OBJECTID":266502},"geometry":{"x":169635.41999999993,"y":2550432.1199999992}},{"attributes":{"ID":266507,"DIS_CODE":0,"TOWNNAME":"安南區","LI":"安順里","LIN":"14鄰","STREET":"總安街","SECT":"一段","MAREA":" ","LANE":"１４６巷","ALLEY":" ","HOUSE_NO":"１２０號","E_COORD97":169636.22,"N_COORD97":2550442.6000000001,"ADDRESS":"總安街一段１４６巷１２０號","OBJECTID":266503},"geometry":{"x":169636.22000000067,"y":2550442.6000000015}},{"attributes":{"ID":266508,"DIS_CODE":0,"TOWNNAME":"安南區","LI":"安順里","LIN":"14鄰","STREET":"總安街","SECT":"一段","MAREA":" ","LANE":"１４６巷","ALLEY":" ","HOUSE_NO":"１２２號","E_COORD97":169635.89999999999,"N_COORD97":2550446.8799999999,"ADDRESS":"總安街一段１４６巷１２２號","OBJECTID":266504},"geometry":{"x":169635.90000000037,"y":2550446.8800000008}},{"attributes":{"ID":266509,"DIS_CODE":0,"TOWNNAME":"安南區","LI":"安順里","LIN":"14鄰","STREET":"總安街","SECT":"一段","MAREA":" ","LANE":"１４６巷","ALLEY":" ","HOUSE_NO":"１２６號","E_COORD97":169636.54000000001,"N_COORD97":2550451.0099999998,"ADDRESS":"總安街一段１４６巷１２６號","OBJECTID":266505},"geometry":{"x":169636.54000000004,"y":2550451.0099999998}},{"attributes":{"ID":266510,"DIS_CODE":0,"TOWNNAME":"安南區","LI":"安順里","LIN":"14鄰","STREET":"總安街","SECT":"一段","MAREA":" ","LANE":"１４６巷","ALLEY":" ","HOUSE_NO":"１２８號","E_COORD97":169637.01000000001,"N_COORD97":2550454.8199999998,"ADDRESS":"總安街一段１４６巷１２８號","OBJECTID":266506},"geometry":{"x":169637.01000000164,"y":2550454.8200000022}},{"attributes":{"ID":266511,"DIS_CODE":0,"TOWNNAME":"安南區","LI":"安順里","LIN":"14鄰","STREET":"總安街","SECT":"一段","MAREA":" ","LANE":"１４６巷","ALLEY":" ","HOUSE_NO":"１３０號","E_COORD97":169637.64999999999,"N_COORD97":2550459.27,"ADDRESS":"總安街一段１４６巷１３０號","OBJECTID":266507},"geometry":{"x":169637.65000000037,"y":2550459.2699999996}},{"attributes":{"ID":266512,"DIS_CODE":0,"TOWNNAME":"安南區","LI":"安順里","LIN":"14鄰","STREET":"總安街","SECT":"一段","MAREA":" ","LANE":"１４６巷","ALLEY":" ","HOUSE_NO":"１３２號","E_COORD97":169637.95999999999,"N_COORD97":2550463.8700000001,"ADDRESS":"總安街一段１４６巷１３２號","OBJECTID":266508},"geometry":{"x":169637.96000000089,"y":2550463.870000001}},{"attributes":{"ID":266513,"DIS_CODE":0,"TOWNNAME":"安南區","LI":"安順里","LIN":"14鄰","STREET":"總安街","SECT":"一段","MAREA":" ","LANE":"１４６巷","ALLEY":" ","HOUSE_NO":"１３６號","E_COORD97":169638.60000000001,"N_COORD97":2550467.8399999999,"ADDRESS":"總安街一段１４６巷１３６號","OBJECTID":266509},"geometry":{"x":169638.60000000056,"y":2550467.8400000017}},{"attributes":{"ID":266514,"DIS_CODE":0,"TOWNNAME":"安南區","LI":"安順里","LIN":"14鄰","STREET":"總安街","SECT":"一段","MAREA":" ","LANE":"１４６巷","ALLEY":" ","HOUSE_NO":"１３８號","E_COORD97":169638.76000000001,"N_COORD97":2550471.9700000002,"ADDRESS":"總安街一段１４６巷１３８號","OBJECTID":266510},"geometry":{"x":169638.76000000164,"y":2550471.9700000007}},{"attributes":{"ID":266515,"DIS_CODE":0,"TOWNNAME":"安南區","LI":"安順里","LIN":"14鄰","STREET":"總安街","SECT":"一段","MAREA":" ","LANE":"１４６巷","ALLEY":" ","HOUSE_NO":"１４０號","E_COORD97":169639.54999999999,"N_COORD97":2550475.9300000002,"ADDRESS":"總安街一段１４６巷１４０號","OBJECTID":266511},"geometry":{"x":169639.54999999981,"y":2550475.9299999997}},{"attributes":{"ID":266516,"DIS_CODE":0,"TOWNNAME":"安南區","LI":"安順里","LIN":"14鄰","STREET":"總安街","SECT":"一段","MAREA":" ","LANE":"１４６巷","ALLEY":" ","HOUSE_NO":"１４６號","E_COORD97":169640.82000000001,"N_COORD97":2550486.5699999998,"ADDRESS":"總安街一段１４６巷１４６號","OBJECTID":266512},"geometry":{"x":169640.82000000123,"y":2550486.5700000022}},{"attributes":{"ID":266517,"DIS_CODE":0,"TOWNNAME":"東區","LI":"忠孝里","LIN":"40鄰","STREET":"崇明路","SECT":" ","MAREA":" ","LANE":"２６６巷","ALLEY":" ","HOUSE_NO":"４號","E_COORD97":169892.48000000001,"N_COORD97":2542059.71,"ADDRESS":"崇明路２６６巷４號","OBJECTID":266513},"geometry":{"x":169892.48000000138,"y":2542059.7100000009}},{"attributes":{"ID":266518,"DIS_CODE":0,"TOWNNAME":"中西區","LI":"西湖里","LIN":"34鄰","STREET":"西湖街","SECT":" ","MAREA":" ","LANE":" ","ALLEY":" ","HOUSE_NO":"６５號","E_COORD97":166421.39000000001,"N_COORD97":2544891.1099999999,"ADDRESS":"西湖街６５號","OBJECTID":266514},"geometry":{"x":166421.38999999966,"y":2544891.1100000013}},{"attributes":{"ID":266519,"DIS_CODE":0,"TOWNNAME":"中西區","LI":"西湖里","LIN":"34鄰","STREET":"西湖街","SECT":" ","MAREA":" ","LANE":" ","ALLEY":" ","HOUSE_NO":"６７號","E_COORD97":166415.79999999999,"N_COORD97":2544891.6200000001,"ADDRESS":"西湖街６７號","OBJECTID":266515},"geometry":{"x":166415.80000000168,"y":2544891.620000001}},{"attributes":{"ID":266520,"DIS_CODE":0,"TOWNNAME":"北區","LI":"安民里","LIN":"3鄰","STREET":"海安路","SECT":"三段","MAREA":" ","LANE":" ","ALLEY":" ","HOUSE_NO":"５０號","E_COORD97":167944.79000000001,"N_COORD97":2544709.52,"ADDRESS":"海安路三段５０號","OBJECTID":266516},"geometry":{"x":167944.79000000004,"y":2544709.5200000014}},{"attributes":{"ID":266521,"DIS_CODE":0,"TOWNNAME":"北區","LI":"安民里","LIN":"3鄰","STREET":"國華街","SECT":"四段","MAREA":" ","LANE":" ","ALLEY":" ","HOUSE_NO":"３７號","E_COORD97":168023.39999999999,"N_COORD97":2544669.54,"ADDRESS":"國華街四段３７號","OBJECTID":266517},"geometry":{"x":168023.4000000013,"y":2544669.5399999991}},{"attributes":{"ID":266522,"DIS_CODE":0,"TOWNNAME":"仁德區","LI":"後壁里","LIN":"14鄰","STREET":"德善路","SECT":" ","MAREA":" ","LANE":"１９８巷","ALLEY":" ","HOUSE_NO":"１２之１１號","E_COORD97":173671.06,"N_COORD97":2538670.9399999999,"ADDRESS":"德善路１９８巷１２之１１號","OBJECTID":266518},"geometry":{"x":173671.06000000145,"y":2538670.9400000032}},{"attributes":{"ID":266523,"DIS_CODE":0,"TOWNNAME":"仁德區","LI":"後壁里","LIN":"14鄰","STREET":"德善路","SECT":" ","MAREA":" ","LANE":"１９８巷","ALLEY":" ","HOUSE_NO":"１２之８號","E_COORD97":173658.92999999999,"N_COORD97":2538679.1899999999,"ADDRESS":"德善路１９８巷１２之８號","OBJECTID":266519},"geometry":{"x":173658.93000000063,"y":2538679.1900000032}},{"attributes":{"ID":266524,"DIS_CODE":0,"TOWNNAME":"歸仁區","LI":"南保里","LIN":"33鄰","STREET":"民權八街","SECT":" ","MAREA":" ","LANE":"５３巷","ALLEY":" ","HOUSE_NO":"２號","E_COORD97":176806.48999999999,"N_COORD97":2540981.29,"ADDRESS":"民權八街５３巷２號","OBJECTID":266520},"geometry":{"x":176806.49000000209,"y":2540981.290000001}},{"attributes":{"ID":266525,"DIS_CODE":0,"TOWNNAME":"仁德區","LI":"成功里","LIN":"14鄰","STREET":"全福路","SECT":" ","MAREA":" ","LANE":"７５巷","ALLEY":" ","HOUSE_NO":"５號","E_COORD97":171020.59,"N_COORD97":2539328.9900000002,"ADDRESS":"全福路７５巷５號","OBJECTID":266521},"geometry":{"x":171020.59000000078,"y":2539328.9900000039}},{"attributes":{"ID":266526,"DIS_CODE":0,"TOWNNAME":"歸仁區","LI":"看東里","LIN":"14鄰","STREET":"忠孝南路","SECT":" ","MAREA":" ","LANE":"２５巷","ALLEY":" ","HOUSE_NO":"１３號","E_COORD97":178563.51000000001,"N_COORD97":2540567.6400000001,"ADDRESS":"忠孝南路２５巷１３號","OBJECTID":266522},"geometry":{"x":178563.50999999978,"y":2540567.6400000006}},{"attributes":{"ID":266527,"DIS_CODE":0,"TOWNNAME":"歸仁區","LI":"後市里","LIN":"14鄰","STREET":"中山路","SECT":"二段","MAREA":" ","LANE":"１８３巷","ALLEY":" ","HOUSE_NO":"５號","E_COORD97":177209.69,"N_COORD97":2540779.25,"ADDRESS":"中山路二段１８３巷５號","OBJECTID":266523},"geometry":{"x":177209.69000000041,"y":2540779.2500000019}},{"attributes":{"ID":266528,"DIS_CODE":0,"TOWNNAME":"歸仁區","LI":"六甲里","LIN":"20鄰","STREET":"中正南路","SECT":"一段","MAREA":" ","LANE":"７３８巷","ALLEY":" ","HOUSE_NO":"８號","E_COORD97":176430.491022,"N_COORD97":2539704.7078499999,"ADDRESS":"中正南路一段７３８巷８號","OBJECTID":266524},"geometry":{"x":176430.49102200102,"y":2539704.7078450006}},{"attributes":{"ID":266529,"DIS_CODE":0,"TOWNNAME":"歸仁區","LI":"六甲里","LIN":"38鄰","STREET":"六甲八街","SECT":" ","MAREA":" ","LANE":"１４９巷","ALLEY":" ","HOUSE_NO":"８號","E_COORD97":175284.976173,"N_COORD97":2539691.53168,"ADDRESS":"六甲八街１４９巷８號","OBJECTID":266525},"geometry":{"x":175284.97617300134,"y":2539691.5316770002}},{"attributes":{"ID":266530,"DIS_CODE":0,"TOWNNAME":"北區","LI":"賢北里","LIN":"14鄰","STREET":"賢北街","SECT":" ","MAREA":" ","LANE":"５７巷","ALLEY":" ","HOUSE_NO":"２０號","E_COORD97":166185.01000000001,"N_COORD97":2545461.8199999998,"ADDRESS":"賢北街５７巷２０號","OBJECTID":266526},"geometry":{"x":166185.00999999978,"y":2545461.8200000003}},{"attributes":{"ID":266531,"DIS_CODE":0,"TOWNNAME":"北區","LI":"賢北里","LIN":"14鄰","STREET":"賢北街","SECT":" ","MAREA":" ","LANE":"５７巷","ALLEY":" ","HOUSE_NO":"２４號","E_COORD97":166179.89000000001,"N_COORD97":2545451.8999999999,"ADDRESS":"賢北街５７巷２４號","OBJECTID":266527},"geometry":{"x":166179.8900000006,"y":2545451.9000000004}},{"attributes":{"ID":266532,"DIS_CODE":0,"TOWNNAME":"北區","LI":"賢北里","LIN":"14鄰","STREET":"賢北街","SECT":" ","MAREA":" ","LANE":"５７巷","ALLEY":" ","HOUSE_NO":"２６號","E_COORD97":166175.39999999999,"N_COORD97":2545449.8100000001,"ADDRESS":"賢北街５７巷２６號","OBJECTID":266528},"geometry":{"x":166175.4000000013,"y":2545449.8099999987}},{"attributes":{"ID":266533,"DIS_CODE":0,"TOWNNAME":"北區","LI":"安民里","LIN":"3鄰","STREET":"國華街","SECT":"四段","MAREA":" ","LANE":" ","ALLEY":" ","HOUSE_NO":"４１號","E_COORD97":168022.51999999999,"N_COORD97":2544680.6299999999,"ADDRESS":"國華街四段４１號","OBJECTID":266529},"geometry":{"x":168022.51999999955,"y":2544680.6300000008}},{"attributes":{"ID":266534,"DIS_CODE":0,"TOWNNAME":"北區","LI":"賢北里","LIN":"14鄰","STREET":"賢北街","SECT":" ","MAREA":" ","LANE":"５７巷","ALLEY":" ","HOUSE_NO":"２８號","E_COORD97":166170.57000000001,"N_COORD97":2545448.0600000001,"ADDRESS":"賢北街５７巷２８號","OBJECTID":266530},"geometry":{"x":166170.57000000216,"y":2545448.0600000005}},{"attributes":{"ID":266535,"DIS_CODE":0,"TOWNNAME":"北區","LI":"賢北里","LIN":"14鄰","STREET":"賢北街","SECT":" ","MAREA":" ","LANE":"５７巷","ALLEY":" ","HOUSE_NO":"３０號","E_COORD97":166166.32999999999,"N_COORD97":2545446.0699999998,"ADDRESS":"賢北街５７巷３０號","OBJECTID":266531},"geometry":{"x":166166.33000000007,"y":2545446.0700000022}},{"attributes":{"ID":266536,"DIS_CODE":0,"TOWNNAME":"北區","LI":"賢北里","LIN":"14鄰","STREET":"賢北街","SECT":" ","MAREA":" ","LANE":"５７巷","ALLEY":" ","HOUSE_NO":"３２號","E_COORD97":166161.92999999999,"N_COORD97":2545444.0899999999,"ADDRESS":"賢北街５７巷３２號","OBJECTID":266532},"geometry":{"x":166161.9299999997,"y":2545444.0900000036}},{"attributes":{"ID":266537,"DIS_CODE":0,"TOWNNAME":"北區","LI":"賢北里","LIN":"14鄰","STREET":"賢北街","SECT":" ","MAREA":" ","LANE":"５７巷","ALLEY":" ","HOUSE_NO":"３６號","E_COORD97":166153.44,"N_COORD97":2545440.5699999998,"ADDRESS":"賢北街５７巷３６號","OBJECTID":266533},"geometry":{"x":166153.44000000134,"y":2545440.5700000003}},{"attributes":{"ID":266538,"DIS_CODE":0,"TOWNNAME":"北區","LI":"賢北里","LIN":"14鄰","STREET":"賢北街","SECT":" ","MAREA":" ","LANE":"５７巷","ALLEY":" ","HOUSE_NO":"３８號","E_COORD97":166149.14999999999,"N_COORD97":2545438.71,"ADDRESS":"賢北街５７巷３８號","OBJECTID":266534},"geometry":{"x":166149.15000000037,"y":2545438.7100000028}},{"attributes":{"ID":266539,"DIS_CODE":0,"TOWNNAME":"北區","LI":"賢北里","LIN":"14鄰","STREET":"賢北街","SECT":" ","MAREA":" ","LANE":"５７巷","ALLEY":" ","HOUSE_NO":"４０號","E_COORD97":166144.91,"N_COORD97":2545436.8799999999,"ADDRESS":"賢北街５７巷４０號","OBJECTID":266535},"geometry":{"x":166144.91000000108,"y":2545436.879999999}},{"attributes":{"ID":266540,"DIS_CODE":0,"TOWNNAME":"歸仁區","LI":"西埔里","LIN":"12鄰","STREET":"西埔一街","SECT":" ","MAREA":" ","LANE":"１８５巷","ALLEY":" ","HOUSE_NO":"１６號","E_COORD97":176965.34,"N_COORD97":2544668.25,"ADDRESS":"西埔一街１８５巷１６號","OBJECTID":266536},"geometry":{"x":176965.34000000078,"y":2544668.2500000019}},{"attributes":{"ID":266541,"DIS_CODE":0,"TOWNNAME":"歸仁區","LI":"文化里","LIN":"13鄰","STREET":"大德路","SECT":" ","MAREA":" ","LANE":"１９３巷","ALLEY":" ","HOUSE_NO":"１３號","E_COORD97":177331.12,"N_COORD97":2541487.3300000001,"ADDRESS":"大德路１９３巷１３號","OBJECTID":266537},"geometry":{"x":177331.12000000197,"y":2541487.3300000019}},{"attributes":{"ID":266542,"DIS_CODE":0,"TOWNNAME":"歸仁區","LI":"大潭里","LIN":"13鄰","STREET":"長榮路","SECT":"一段","MAREA":" ","LANE":"１６３巷","ALLEY":" ","HOUSE_NO":"５號","E_COORD97":174960.26000000001,"N_COORD97":2534615.2799999998,"ADDRESS":"長榮路一段１６３巷５號","OBJECTID":266538},"geometry":{"x":174960.26000000071,"y":2534615.2799999993}},{"attributes":{"ID":266543,"DIS_CODE":0,"TOWNNAME":"安平區","LI":"海頭里","LIN":"14鄰","STREET":"安北路","SECT":" ","MAREA":" ","LANE":"１３１巷","ALLEY":" ","HOUSE_NO":"３６號","E_COORD97":165924.14999999999,"N_COORD97":2543601.3300000001,"ADDRESS":"安北路１３１巷３６號","OBJECTID":266539},"geometry":{"x":165924.15000000224,"y":2543601.3300000001}},{"attributes":{"ID":266544,"DIS_CODE":0,"TOWNNAME":"中西區","LI":"普濟里","LIN":"3鄰","STREET":"民族路","SECT":"三段","MAREA":" ","LANE":" ","ALLEY":" ","HOUSE_NO":"３６號六樓","E_COORD97":167863.59,"N_COORD97":2544283.79,"ADDRESS":"民族路三段３６號六樓","OBJECTID":266540},"geometry":{"x":167863.59000000078,"y":2544283.790000001}},{"attributes":{"ID":266545,"DIS_CODE":0,"TOWNNAME":"安平區","LI":"海頭里","LIN":"14鄰","STREET":"安北路","SECT":" ","MAREA":" ","LANE":"１３１巷","ALLEY":" ","HOUSE_NO":"２８號","E_COORD97":164072.17999999999,"N_COORD97":2544796.0699999998,"ADDRESS":"安北路１３１巷２８號","OBJECTID":266541},"geometry":{"x":164072.18000000156,"y":2544796.0700000003}},{"attributes":{"ID":266546,"DIS_CODE":0,"TOWNNAME":"新營區","LI":"中營里","LIN":"14鄰","STREET":"東山路","SECT":" ","MAREA":" ","LANE":"１９巷","ALLEY":" ","HOUSE_NO":"８８號","E_COORD97":181490.20999999999,"N_COORD97":2578794.9900000002,"ADDRESS":"東山路１９巷８８號","OBJECTID":266542},"geometry":{"x":181490.21000000183,"y":2578794.9900000002}},{"attributes":{"ID":266547,"DIS_CODE":0,"TOWNNAME":"新營區","LI":"中營里","LIN":"14鄰","STREET":"東昇街","SECT":" ","MAREA":" ","LANE":"１７７巷","ALLEY":" ","HOUSE_NO":"６號","E_COORD97":181922.82999999999,"N_COORD97":2579070.96,"ADDRESS":"東昇街１７７巷６號","OBJECTID":266543},"geometry":{"x":181922.83000000007,"y":2579070.9600000009}},{"attributes":{"ID":266548,"DIS_CODE":0,"TOWNNAME":"新營區","LI":"新北里","LIN":"14鄰","STREET":"南新街","SECT":" ","MAREA":" ","LANE":"１３巷","ALLEY":" ","HOUSE_NO":"６０號","E_COORD97":179268.63,"N_COORD97":2578810.9700000002,"ADDRESS":"南新街１３巷６０號","OBJECTID":266544},"geometry":{"x":179268.63000000082,"y":2578810.9700000025}},{"attributes":{"ID":266549,"DIS_CODE":0,"TOWNNAME":"歸仁區","LI":"六甲里","LIN":"39鄰","STREET":"六甲八街","SECT":" ","MAREA":" ","LANE":"１４９巷","ALLEY":" ","HOUSE_NO":"１１４號","E_COORD97":175220.39999999999,"N_COORD97":2539870.73,"ADDRESS":"六甲八街１４９巷１１４號","OBJECTID":266545},"geometry":{"x":175220.40000000037,"y":2539870.7300000023}},{"attributes":{"ID":266550,"DIS_CODE":0,"TOWNNAME":"歸仁區","LI":"文化里","LIN":"13鄰","STREET":"大德路","SECT":" ","MAREA":" ","LANE":"１９３巷","ALLEY":" ","HOUSE_NO":"５號","E_COORD97":177305.26999999999,"N_COORD97":2541488.3300000001,"ADDRESS":"大德路１９３巷５號","OBJECTID":266546},"geometry":{"x":177305.26999999955,"y":2541488.3300000001}},{"attributes":{"ID":266551,"DIS_CODE":0,"TOWNNAME":"南區","LI":"鯤鯓里","LIN":"14鄰","STREET":"鯤鯓路","SECT":" ","MAREA":" ","LANE":"１０２巷","ALLEY":" ","HOUSE_NO":"１６８號","E_COORD97":165057.51999999999,"N_COORD97":2540296.3300000001,"ADDRESS":"鯤鯓路１０２巷１６８號","OBJECTID":266547},"geometry":{"x":165057.51999999955,"y":2540296.3300000038}},{"attributes":{"ID":266552,"DIS_CODE":0,"TOWNNAME":"南區","LI":"鯤鯓里","LIN":"14鄰","STREET":"鯤鯓路","SECT":" ","MAREA":" ","LANE":"１０２巷","ALLEY":" ","HOUSE_NO":"１７０號","E_COORD97":165050.14999999999,"N_COORD97":2540294.7599999998,"ADDRESS":"鯤鯓路１０２巷１７０號","OBJECTID":266548},"geometry":{"x":165050.1500000013,"y":2540294.7599999998}},{"attributes":{"ID":266553,"DIS_CODE":0,"TOWNNAME":"南區","LI":"鯤鯓里","LIN":"14鄰","STREET":"鯤鯓路","SECT":" ","MAREA":" ","LANE":"１０２巷","ALLEY":" ","HOUSE_NO":"１７２號","E_COORD97":165045.67999999999,"N_COORD97":2540294.1600000001,"ADDRESS":"鯤鯓路１０２巷１７２號","OBJECTID":266549},"geometry":{"x":165045.68000000063,"y":2540294.1600000039}},{"attributes":{"ID":266554,"DIS_CODE":0,"TOWNNAME":"南區","LI":"鯤鯓里","LIN":"14鄰","STREET":"鯤鯓路","SECT":" ","MAREA":" ","LANE":"１０２巷","ALLEY":" ","HOUSE_NO":"１７４之１號","E_COORD97":165033.48000000001,"N_COORD97":2540287.7599999998,"ADDRESS":"鯤鯓路１０２巷１７４之１號","OBJECTID":266550},"geometry":{"x":165033.48000000045,"y":2540287.7599999998}},{"attributes":{"ID":266555,"DIS_CODE":0,"TOWNNAME":"南區","LI":"鯤鯓里","LIN":"14鄰","STREET":"鯤鯓路","SECT":" ","MAREA":" ","LANE":"１０２巷","ALLEY":" ","HOUSE_NO":"１７４號","E_COORD97":165040.73000000001,"N_COORD97":2540293.0699999998,"ADDRESS":"鯤鯓路１０２巷１７４號","OBJECTID":266551},"geometry":{"x":165040.73000000138,"y":2540293.0700000003}},{"attributes":{"ID":266556,"DIS_CODE":0,"TOWNNAME":"南區","LI":"鯤鯓里","LIN":"14鄰","STREET":"鯤鯓路","SECT":" ","MAREA":" ","LANE":"１０２巷","ALLEY":" ","HOUSE_NO":"１７８號","E_COORD97":165031.91,"N_COORD97":2540297.8999999999,"ADDRESS":"鯤鯓路１０２巷１７８號","OBJECTID":266552},"geometry":{"x":165031.91000000015,"y":2540297.9000000004}},{"attributes":{"ID":266557,"DIS_CODE":0,"TOWNNAME":"南區","LI":"鯤鯓里","LIN":"14鄰","STREET":"鯤鯓路","SECT":" ","MAREA":" ","LANE":"１０２巷","ALLEY":" ","HOUSE_NO":"１８０號","E_COORD97":165025.26999999999,"N_COORD97":2540292.8300000001,"ADDRESS":"鯤鯓路１０２巷１８０號","OBJECTID":266553},"geometry":{"x":165025.26999999955,"y":2540292.8300000038}},{"attributes":{"ID":266558,"DIS_CODE":0,"TOWNNAME":"南區","LI":"鯤鯓里","LIN":"14鄰","STREET":"鯤鯓路","SECT":" ","MAREA":" ","LANE":"１０２巷","ALLEY":" ","HOUSE_NO":"１８２號","E_COORD97":165016.69,"N_COORD97":2540292.3500000001,"ADDRESS":"鯤鯓路１０２巷１８２號","OBJECTID":266554},"geometry":{"x":165016.69000000041,"y":2540292.3500000015}},{"attributes":{"ID":266559,"DIS_CODE":0,"TOWNNAME":"南區","LI":"鯤鯓里","LIN":"14鄰","STREET":"鯤鯓路","SECT":" ","MAREA":" ","LANE":"１８４巷","ALLEY":" ","HOUSE_NO":"２１號","E_COORD97":164995.34,"N_COORD97":2540291.6299999999,"ADDRESS":"鯤鯓路１８４巷２１號","OBJECTID":266555},"geometry":{"x":164995.34000000078,"y":2540291.629999999}},{"attributes":{"ID":266560,"DIS_CODE":0,"TOWNNAME":"南區","LI":"鯤鯓里","LIN":"14鄰","STREET":"鯤鯓路","SECT":" ","MAREA":" ","LANE":"１９４巷","ALLEY":" ","HOUSE_NO":"３２號","E_COORD97":164993.38,"N_COORD97":2540314.0699999998,"ADDRESS":"鯤鯓路１９４巷３２號","OBJECTID":266556},"geometry":{"x":164993.38000000082,"y":2540314.0700000003}},{"attributes":{"ID":266561,"DIS_CODE":0,"TOWNNAME":"南區","LI":"鯤鯓里","LIN":"14鄰","STREET":"鯤鯓路","SECT":" ","MAREA":" ","LANE":"１９４巷","ALLEY":" ","HOUSE_NO":"３４號","E_COORD97":164992.89999999999,"N_COORD97":2540304.29,"ADDRESS":"鯤鯓路１９４巷３４號","OBJECTID":266557},"geometry":{"x":164992.90000000037,"y":2540304.2899999991}},{"attributes":{"ID":266562,"DIS_CODE":0,"TOWNNAME":"南區","LI":"鯤鯓里","LIN":"14鄰","STREET":"鯤鯓路","SECT":" ","MAREA":" ","LANE":"１９４巷","ALLEY":" ","HOUSE_NO":"３６號","E_COORD97":165009.09,"N_COORD97":2540308.52,"ADDRESS":"鯤鯓路１９４巷３６號","OBJECTID":266558},"geometry":{"x":165009.09000000078,"y":2540308.5200000014}},{"attributes":{"ID":266563,"DIS_CODE":0,"TOWNNAME":"北區","LI":"延平里","LIN":"14鄰","STREET":"長榮路","SECT":"五段","MAREA":" ","LANE":"４０９巷","ALLEY":" ","HOUSE_NO":"１１號","E_COORD97":169308.78,"N_COORD97":2545906.7599999998,"ADDRESS":"長榮路五段４０９巷１１號","OBJECTID":266559},"geometry":{"x":169308.78000000119,"y":2545906.7599999998}},{"attributes":{"ID":266564,"DIS_CODE":0,"TOWNNAME":"北區","LI":"延平里","LIN":"14鄰","STREET":"長榮路","SECT":"五段","MAREA":" ","LANE":"４０９巷","ALLEY":" ","HOUSE_NO":"１５號","E_COORD97":169303.57000000001,"N_COORD97":2545899.7200000002,"ADDRESS":"長榮路五段４０９巷１５號","OBJECTID":266560},"geometry":{"x":169303.57000000123,"y":2545899.7200000025}},{"attributes":{"ID":266565,"DIS_CODE":0,"TOWNNAME":"北區","LI":"延平里","LIN":"14鄰","STREET":"長榮路","SECT":"五段","MAREA":" ","LANE":"４０９巷","ALLEY":" ","HOUSE_NO":"１７號","E_COORD97":169301.59,"N_COORD97":2545895.2000000002,"ADDRESS":"長榮路五段４０９巷１７號","OBJECTID":266561},"geometry":{"x":169301.59000000078,"y":2545895.2000000011}},{"attributes":{"ID":266566,"DIS_CODE":0,"TOWNNAME":"歸仁區","LI":"大潭里","LIN":"14鄰","STREET":"長榮路","SECT":"一段","MAREA":" ","LANE":"１６３巷","ALLEY":" ","HOUSE_NO":"１６號","E_COORD97":174956.41,"N_COORD97":2534631.2799999998,"ADDRESS":"長榮路一段１６３巷１６號","OBJECTID":266562},"geometry":{"x":174956.41000000108,"y":2534631.2800000012}},{"attributes":{"ID":266567,"DIS_CODE":0,"TOWNNAME":"歸仁區","LI":"文化里","LIN":"10鄰","STREET":"民族北街","SECT":" ","MAREA":" ","LANE":"２３１巷","ALLEY":" ","HOUSE_NO":"８號","E_COORD97":177440.60000000001,"N_COORD97":2541441.3300000001,"ADDRESS":"民族北街２３１巷８號","OBJECTID":266563},"geometry":{"x":177440.59999999963,"y":2541441.3300000001}},{"attributes":{"ID":266568,"DIS_CODE":0,"TOWNNAME":"北區","LI":"延平里","LIN":"14鄰","STREET":"長榮路","SECT":"五段","MAREA":" ","LANE":"４０９巷","ALLEY":" ","HOUSE_NO":"１９號","E_COORD97":169298.76999999999,"N_COORD97":2545891.2599999998,"ADDRESS":"長榮路五段４０９巷１９號","OBJECTID":266564},"geometry":{"x":169298.76999999955,"y":2545891.2600000016}},{"attributes":{"ID":266569,"DIS_CODE":0,"TOWNNAME":"北區","LI":"延平里","LIN":"14鄰","STREET":"長榮路","SECT":"五段","MAREA":" ","LANE":"４０９巷","ALLEY":" ","HOUSE_NO":"１號","E_COORD97":169319.79000000001,"N_COORD97":2545926.0800000001,"ADDRESS":"長榮路五段４０９巷１號","OBJECTID":266565},"geometry":{"x":169319.79000000004,"y":2545926.0800000019}},{"attributes":{"ID":266570,"DIS_CODE":0,"TOWNNAME":"北區","LI":"延平里","LIN":"14鄰","STREET":"長榮路","SECT":"五段","MAREA":" ","LANE":"４０９巷","ALLEY":" ","HOUSE_NO":"２１號","E_COORD97":169298.20000000001,"N_COORD97":2545888.1099999999,"ADDRESS":"長榮路五段４０９巷２１號","OBJECTID":266566},"geometry":{"x":169298.20000000019,"y":2545888.1100000013}},{"attributes":{"ID":266571,"DIS_CODE":0,"TOWNNAME":"東區","LI":"東光里","LIN":"34鄰","STREET":"莊敬路","SECT":" ","MAREA":" ","LANE":" ","ALLEY":" ","HOUSE_NO":"２９號","E_COORD97":171325.54000000001,"N_COORD97":2543781.6400000001,"ADDRESS":"莊敬路２９號","OBJECTID":266567},"geometry":{"x":171325.5400000019,"y":2543781.6400000006}},{"attributes":{"ID":266572,"DIS_CODE":0,"TOWNNAME":"北區","LI":"延平里","LIN":"14鄰","STREET":"長榮路","SECT":"五段","MAREA":" ","LANE":"４０９巷","ALLEY":" ","HOUSE_NO":"２３號","E_COORD97":169296.51000000001,"N_COORD97":2545884.1600000001,"ADDRESS":"長榮路五段４０９巷２３號","OBJECTID":266568},"geometry":{"x":169296.51000000071,"y":2545884.1600000001}},{"attributes":{"ID":266573,"DIS_CODE":0,"TOWNNAME":"北區","LI":"延平里","LIN":"14鄰","STREET":"長榮路","SECT":"五段","MAREA":" ","LANE":"４０９巷","ALLEY":" ","HOUSE_NO":"３號","E_COORD97":169315.56,"N_COORD97":2545921.4199999999,"ADDRESS":"長榮路五段４０９巷３號","OBJECTID":266569},"geometry":{"x":169315.55999999959,"y":2545921.4200000018}},{"attributes":{"ID":266574,"DIS_CODE":0,"TOWNNAME":"北區","LI":"延平里","LIN":"14鄰","STREET":"長榮路","SECT":"五段","MAREA":" ","LANE":"４０９巷","ALLEY":" ","HOUSE_NO":"５號","E_COORD97":169313.16,"N_COORD97":2545917.6200000001,"ADDRESS":"長榮路五段４０９巷５號","OBJECTID":266570},"geometry":{"x":169313.16000000108,"y":2545917.6200000029}},{"attributes":{"ID":266575,"DIS_CODE":0,"TOWNNAME":"北區","LI":"延平里","LIN":"14鄰","STREET":"長榮路","SECT":"五段","MAREA":" ","LANE":"４０９巷","ALLEY":" ","HOUSE_NO":"７號","E_COORD97":169312.03,"N_COORD97":2545914.23,"ADDRESS":"長榮路五段４０９巷７號","OBJECTID":266571},"geometry":{"x":169312.03000000119,"y":2545914.2300000004}},{"attributes":{"ID":266576,"DIS_CODE":0,"TOWNNAME":"北區","LI":"延平里","LIN":"14鄰","STREET":"長榮路","SECT":"五段","MAREA":" ","LANE":"４０９巷","ALLEY":" ","HOUSE_NO":"９號","E_COORD97":169309.63,"N_COORD97":2545910.4300000002,"ADDRESS":"長榮路五段４０９巷９號","OBJECTID":266572},"geometry":{"x":169309.63000000082,"y":2545910.4300000016}},{"attributes":{"ID":266577,"DIS_CODE":0,"TOWNNAME":"東區","LI":"圍下里","LIN":"3鄰","STREET":"東榮街","SECT":" ","MAREA":" ","LANE":" ","ALLEY":" ","HOUSE_NO":"５９號三樓之１","E_COORD97":169554.89999999999,"N_COORD97":2543364.8500000001,"ADDRESS":"東榮街５９號三樓之１","OBJECTID":266573},"geometry":{"x":169554.90000000037,"y":2543364.8500000015}},{"attributes":{"ID":266578,"DIS_CODE":0,"TOWNNAME":"東區","LI":"圍下里","LIN":"3鄰","STREET":"東榮街","SECT":" ","MAREA":" ","LANE":" ","ALLEY":" ","HOUSE_NO":"５９號三樓之２","E_COORD97":169554.89999999999,"N_COORD97":2543364.8500000001,"ADDRESS":"東榮街５９號三樓之２","OBJECTID":266574},"geometry":{"x":169554.90000000037,"y":2543364.8500000015}},{"attributes":{"ID":266579,"DIS_CODE":0,"TOWNNAME":"北區","LI":"延平里","LIN":"14鄰","STREET":"長榮路","SECT":"五段","MAREA":" ","LANE":"４３５巷","ALLEY":" ","HOUSE_NO":"１０號","E_COORD97":169232.51000000001,"N_COORD97":2545933.0800000001,"ADDRESS":"長榮路五段４３５巷１０號","OBJECTID":266575},"geometry":{"x":169232.51000000071,"y":2545933.0800000019}},{"attributes":{"ID":266580,"DIS_CODE":0,"TOWNNAME":"北區","LI":"延平里","LIN":"14鄰","STREET":"長榮路","SECT":"五段","MAREA":" ","LANE":"４３５巷","ALLEY":" ","HOUSE_NO":"１２號","E_COORD97":169230.26000000001,"N_COORD97":2545930.1299999999,"ADDRESS":"長榮路五段４３５巷１２號","OBJECTID":266576},"geometry":{"x":169230.26000000071,"y":2545930.129999999}},{"attributes":{"ID":266581,"DIS_CODE":0,"TOWNNAME":"東區","LI":"圍下里","LIN":"3鄰","STREET":"東榮街","SECT":" ","MAREA":" ","LANE":" ","ALLEY":" ","HOUSE_NO":"５９號四樓","E_COORD97":169554.89999999999,"N_COORD97":2543364.8500000001,"ADDRESS":"東榮街５９號四樓","OBJECTID":266577},"geometry":{"x":169554.90000000037,"y":2543364.8500000015}},{"attributes":{"ID":266582,"DIS_CODE":0,"TOWNNAME":"東區","LI":"圍下里","LIN":"3鄰","STREET":"東榮街","SECT":" ","MAREA":" ","LANE":" ","ALLEY":" ","HOUSE_NO":"５９號四樓之１","E_COORD97":169554.89999999999,"N_COORD97":2543364.8500000001,"ADDRESS":"東榮街５９號四樓之１","OBJECTID":266578},"geometry":{"x":169554.90000000037,"y":2543364.8500000015}},{"attributes":{"ID":266583,"DIS_CODE":0,"TOWNNAME":"東區","LI":"圍下里","LIN":"3鄰","STREET":"東榮街","SECT":" ","MAREA":" ","LANE":" ","ALLEY":" ","HOUSE_NO":"５９號四樓之２","E_COORD97":169554.89999999999,"N_COORD97":2543364.8500000001,"ADDRESS":"東榮街５９號四樓之２","OBJECTID":266579},"geometry":{"x":169554.90000000037,"y":2543364.8500000015}},{"attributes":{"ID":266584,"DIS_CODE":0,"TOWNNAME":"白河區","LI":"內角里","LIN":"5鄰","STREET":" ","SECT":" ","MAREA":"內角","LANE":" ","ALLEY":" ","HOUSE_NO":"６７號","E_COORD97":192532.84,"N_COORD97":2588523.9500000002,"ADDRESS":"內角６７號","OBJECTID":266580},"geometry":{"x":192532.83999999985,"y":2588523.9500000011}},{"attributes":{"ID":266585,"DIS_CODE":0,"TOWNNAME":"北區","LI":"延平里","LIN":"14鄰","STREET":"長榮路","SECT":"五段","MAREA":" ","LANE":"４３５巷","ALLEY":" ","HOUSE_NO":"１４號","E_COORD97":169228.16,"N_COORD97":2545927.75,"ADDRESS":"長榮路五段４３５巷１４號","OBJECTID":266581},"geometry":{"x":169228.16000000108,"y":2545927.7499999981}},{"attributes":{"ID":266586,"DIS_CODE":0,"TOWNNAME":"北區","LI":"延平里","LIN":"14鄰","STREET":"長榮路","SECT":"五段","MAREA":" ","LANE":"４３５巷","ALLEY":" ","HOUSE_NO":"１６號","E_COORD97":169226.20000000001,"N_COORD97":2545924.8100000001,"ADDRESS":"長榮路五段４３５巷１６號","OBJECTID":266582},"geometry":{"x":169226.20000000112,"y":2545924.8100000042}},{"attributes":{"ID":266587,"DIS_CODE":0,"TOWNNAME":"北區","LI":"延平里","LIN":"14鄰","STREET":"長榮路","SECT":"五段","MAREA":" ","LANE":"４３５巷","ALLEY":" ","HOUSE_NO":"１８號","E_COORD97":169224.72,"N_COORD97":2545922.04,"ADDRESS":"長榮路五段４３５巷１８號","OBJECTID":266583},"geometry":{"x":169224.71999999974,"y":2545922.040000001}},{"attributes":{"ID":266588,"DIS_CODE":0,"TOWNNAME":"北區","LI":"延平里","LIN":"14鄰","STREET":"長榮路","SECT":"五段","MAREA":" ","LANE":"４３５巷","ALLEY":" ","HOUSE_NO":"４號","E_COORD97":169240.51000000001,"N_COORD97":2545943.3100000001,"ADDRESS":"長榮路五段４３５巷４號","OBJECTID":266584},"geometry":{"x":169240.51000000071,"y":2545943.3100000024}},{"attributes":{"ID":266589,"DIS_CODE":0,"TOWNNAME":"歸仁區","LI":"媽廟里","LIN":"14鄰","STREET":"媽廟二街","SECT":" ","MAREA":" ","LANE":"１５巷","ALLEY":" ","HOUSE_NO":"１７號","E_COORD97":177649.67999999999,"N_COORD97":2543779.7200000002,"ADDRESS":"媽廟二街１５巷１７號","OBJECTID":266585},"geometry":{"x":177649.68000000063,"y":2543779.7200000025}},{"attributes":{"ID":266590,"DIS_CODE":0,"TOWNNAME":"歸仁區","LI":"媽廟里","LIN":"14鄰","STREET":"媽廟二街","SECT":" ","MAREA":" ","LANE":"１５巷","ALLEY":" ","HOUSE_NO":"３１號","E_COORD97":177653.98000000001,"N_COORD97":2543817.7200000002,"ADDRESS":"媽廟二街１５巷３１號","OBJECTID":266586},"geometry":{"x":177653.98000000045,"y":2543817.7200000025}},{"attributes":{"ID":266591,"DIS_CODE":0,"TOWNNAME":"歸仁區","LI":"西埔里","LIN":"14鄰","STREET":"西埔二街","SECT":" ","MAREA":" ","LANE":"８７巷","ALLEY":" ","HOUSE_NO":"２７號","E_COORD97":176882.29000000001,"N_COORD97":2544700.25,"ADDRESS":"西埔二街８７巷２７號","OBJECTID":266587},"geometry":{"x":176882.2900000019,"y":2544700.25}},{"attributes":{"ID":266592,"DIS_CODE":0,"TOWNNAME":"北區","LI":"實踐里","LIN":"14鄰","STREET":"大武街","SECT":" ","MAREA":" ","LANE":"１９９巷","ALLEY":" ","HOUSE_NO":"１號","E_COORD97":169604.01999999999,"N_COORD97":2546044.8799999999,"ADDRESS":"大武街１９９巷１號","OBJECTID":266588},"geometry":{"x":169604.01999999955,"y":2546044.8800000027}},{"attributes":{"ID":266593,"DIS_CODE":0,"TOWNNAME":"北區","LI":"文元里","LIN":"14鄰","STREET":"文賢路","SECT":" ","MAREA":" ","LANE":"１０３０巷","ALLEY":" ","HOUSE_NO":"１號","E_COORD97":167390.13,"N_COORD97":2546082.3799999999,"ADDRESS":"文賢路１０３０巷１號","OBJECTID":266589},"geometry":{"x":167390.13000000175,"y":2546082.3800000008}},{"attributes":{"ID":266594,"DIS_CODE":0,"TOWNNAME":"北區","LI":"文元里","LIN":"14鄰","STREET":"文賢路","SECT":" ","MAREA":" ","LANE":"１０３０巷","ALLEY":" ","HOUSE_NO":"１號之１","E_COORD97":167394.56,"N_COORD97":2546084.02,"ADDRESS":"文賢路１０３０巷１號之１","OBJECTID":266590},"geometry":{"x":167394.55999999959,"y":2546084.0199999996}},{"attributes":{"ID":266595,"DIS_CODE":0,"TOWNNAME":"北區","LI":"文元里","LIN":"14鄰","STREET":"文賢路","SECT":" ","MAREA":" ","LANE":"１０３０巷","ALLEY":" ","HOUSE_NO":"１號之２","E_COORD97":167399.48999999999,"N_COORD97":2546083.2000000002,"ADDRESS":"文賢路１０３０巷１號之２","OBJECTID":266591},"geometry":{"x":167399.49000000022,"y":2546083.1999999974}},{"attributes":{"ID":266596,"DIS_CODE":0,"TOWNNAME":"北區","LI":"新勝里","LIN":"14鄰","STREET":"長榮路","SECT":"五段","MAREA":" ","LANE":"１７５巷","ALLEY":" ","HOUSE_NO":"１８號","E_COORD97":170008.10999999999,"N_COORD97":2545792.25,"ADDRESS":"長榮路五段１７５巷１８號","OBJECTID":266592},"geometry":{"x":170008.1100000022,"y":2545792.2500000037}},{"attributes":{"ID":266597,"DIS_CODE":0,"TOWNNAME":"北區","LI":"新勝里","LIN":"14鄰","STREET":"長榮路","SECT":"五段","MAREA":" ","LANE":"１７５巷","ALLEY":" ","HOUSE_NO":"２０號","E_COORD97":170003.95000000001,"N_COORD97":2545791.21,"ADDRESS":"長榮路五段１７５巷２０號","OBJECTID":266593},"geometry":{"x":170003.95000000205,"y":2545791.2100000028}},{"attributes":{"ID":266598,"DIS_CODE":0,"TOWNNAME":"北區","LI":"新勝里","LIN":"14鄰","STREET":"長榮路","SECT":"五段","MAREA":" ","LANE":"１７５巷","ALLEY":" ","HOUSE_NO":"２２號","E_COORD97":169999.85000000001,"N_COORD97":2545791.7999999998,"ADDRESS":"長榮路五段１７５巷２２號","OBJECTID":266594},"geometry":{"x":169999.84999999963,"y":2545791.8000000007}},{"attributes":{"ID":266599,"DIS_CODE":0,"TOWNNAME":"北區","LI":"新勝里","LIN":"14鄰","STREET":"長榮路","SECT":"五段","MAREA":" ","LANE":"１７５巷","ALLEY":" ","HOUSE_NO":"２４號","E_COORD97":169995.87,"N_COORD97":2545790.6200000001,"ADDRESS":"長榮路五段１７５巷２４號","OBJECTID":266595},"geometry":{"x":169995.86999999918,"y":2545790.620000001}},{"attributes":{"ID":266600,"DIS_CODE":0,"TOWNNAME":"北區","LI":"新勝里","LIN":"14鄰","STREET":"長榮路","SECT":"五段","MAREA":" ","LANE":"１７５巷","ALLEY":" ","HOUSE_NO":"２６號","E_COORD97":169991.82999999999,"N_COORD97":2545791.73,"ADDRESS":"長榮路五段１７５巷２６號","OBJECTID":266596},"geometry":{"x":169991.83000000101,"y":2545791.7300000004}},{"attributes":{"ID":266601,"DIS_CODE":0,"TOWNNAME":"北區","LI":"新勝里","LIN":"14鄰","STREET":"長榮路","SECT":"五段","MAREA":" ","LANE":"１７５巷","ALLEY":" ","HOUSE_NO":"２８號","E_COORD97":169987.73000000001,"N_COORD97":2545790.5600000001,"ADDRESS":"長榮路五段１７５巷２８號","OBJECTID":266597},"geometry":{"x":169987.73000000138,"y":2545790.5599999987}},{"attributes":{"ID":266602,"DIS_CODE":0,"TOWNNAME":"北區","LI":"新勝里","LIN":"14鄰","STREET":"長榮路","SECT":"五段","MAREA":" ","LANE":"１７５巷","ALLEY":" ","HOUSE_NO":"３０號","E_COORD97":169983.57000000001,"N_COORD97":2545791.5299999998,"ADDRESS":"長榮路五段１７５巷３０號","OBJECTID":266598},"geometry":{"x":169983.57000000123,"y":2545791.5299999993}},{"attributes":{"ID":266603,"DIS_CODE":0,"TOWNNAME":"北區","LI":"新勝里","LIN":"14鄰","STREET":"長榮路","SECT":"五段","MAREA":" ","LANE":"１７５巷","ALLEY":" ","HOUSE_NO":"３２號","E_COORD97":169979.34,"N_COORD97":2545790.1699999999,"ADDRESS":"長榮路五段１７５巷３２號","OBJECTID":266599},"geometry":{"x":169979.34000000078,"y":2545790.1700000018}},{"attributes":{"ID":266604,"DIS_CODE":0,"TOWNNAME":"歸仁區","LI":"八甲里","LIN":"14鄰","STREET":"大明街","SECT":" ","MAREA":" ","LANE":"１３８巷","ALLEY":" ","HOUSE_NO":"３１號","E_COORD97":178260.28,"N_COORD97":2541882.25,"ADDRESS":"大明街１３８巷３１號","OBJECTID":266600},"geometry":{"x":178260.28000000026,"y":2541882.25}}]}